Workbook

Sheet Golden Set
A1: Team 8 golden test set: final labels
A2: 180 tickets from rows 8000-8999, labelled independently by two team members (Hakim & Glenn) and reconciled under the labelling protocol . Every final label is a live formula: a Resolution Log decision if the labellers disagreed; otherwise the Consistency Check label if the agreed label was changed; otherwise the agreed label.
A4: row_id | B4: Labeler 1 | C4: Labeler 2 | D4: Final label | E4: Source of final label | F4: Differs from Labeler 1 | G4: Differs from Labeler 2
A5: 8022 | B5: =INDEX('Labeler 1'!$C$2:$C$181,MATCH(A5,'Labeler 1'!$A$2:$A$181,0)) -> Credit reporting | C5: =INDEX('Labeler 2'!$C$2:$C$181,MATCH(A5,'Labeler 2'!$A$2:$A$181,0)) -> Credit reporting | D5: =IF(COUNTIF('Resolution Log'!$A$5:$A$24,A5)>0,INDEX('Resolution Log'!$G$5:$G$24,MATCH(A5,'Resolution Log'!$A$5:$A$24,0)),IF(COUNTIFS('Consistency Check'!$A$5:$A$99,A5,'Consistency Check'!$D$5:$D$99,"No")>0,INDEX('Consistency Check'!$E$5:$E$99,MATCH(A5,'Consistency Check'!$A$5:$A$99,0)),C5)) -> Credit reporting | E5: =IF(COUNTIF('Resolution Log'!$A$5:$A$24,A5)>0,"Resolution Log (disagreement)",IF(COUNTIFS('Consistency Check'!$A$5:$A$99,A5,'Consistency Check'!$D$5:$D$99,"No")>0,"Consistency Check (agreed label changed)",IF(COUNTIF('Consistency Check'!$A$5:$A$99,A5)>0,"Consistency Check (agreed label confirmed)","Agreed label"))) -> Agreed label | F5: =IF(D5<>B5,"Yes","") | G5: =IF(D5<>C5,"Yes","")
A6: 8024 | B6: =INDEX('Labeler 1'!$C$2:$C$181,MATCH(A6,'Labeler 1'!$A$2:$A$181,0)) -> Money transfer or service | C6: =INDEX('Labeler 2'!$C$2:$C$181,MATCH(A6,'Labeler 2'!$A$2:$A$181,0)) -> Money transfer or service | D6: =IF(COUNTIF('Resolution Log'!$A$5:$A$24,A6)>0,INDEX('Resolution Log'!$G$5:$G$24,MATCH(A6,'Resolution Log'!$A$5:$A$24,0)),IF(COUNTIFS('Consistency Check'!$A$5:$A$99,A6,'Consistency Check'!$D$5:$D$99,"No")>0,INDEX('Consistency Check'!$E$5:$E$99,MATCH(A6,'Consistency Check'!$A$5:$A$99,0)),C6)) -> Money transfer or service | E6: =IF(COUNTIF('Resolution Log'!$A$5:$A$24,A6)>0,"Resolution Log (disagreement)",IF(COUNTIFS('Consistency Check'!$A$5:$A$99,A6,'Consistency Check'!$D$5:$D$99,"No")>0,"Consistency Check (agreed label changed)",IF(COUNTIF('Consistency Check'!$A$5:$A$99,A6)>0,"Consistency Check (agreed label confirmed)","Agreed label"))) -> Consistency Check (agreed label confirmed) | F6: =IF(D6<>B6,"Yes","") | G6: =IF(D6<>C6,"Yes","")
A7: 8033 | B7: =INDEX('Labeler 1'!$C$2:$C$181,MATCH(A7,'Labeler 1'!$A$2:$A$181,0)) -> Credit card | C7: =INDEX('Labeler 2'!$C$2:$C$181,MATCH(A7,'Labeler 2'!$A$2:$A$181,0)) -> Credit card | D7: =IF(COUNTIF('Resolution Log'!$A$5:$A$24,A7)>0,INDEX('Resolution Log'!$G$5:$G$24,MATCH(A7,'Resolution Log'!$A$5:$A$24,0)),IF(COUNTIFS('Consistency Check'!$A$5:$A$99,A7,'Consistency Check'!$D$5:$D$99,"No")>0,INDEX('Consistency Check'!$E$5:$E$99,MATCH(A7,'Consistency Check'!$A$5:$A$99,0)),C7)) -> Credit card | E7: =IF(COUNTIF('Resolution Log'!$A$5:$A$24,A7)>0,"Resolution Log (disagreement)",IF(COUNTIFS('Consistency Check'!$A$5:$A$99,A7,'Consistency Check'!$D$5:$D$99,"No")>0,"Consistency Check (agreed label changed)",IF(COUNTIF('Consistency Check'!$A$5:$A$99,A7)>0,"Consistency Check (agreed label confirmed)","Agreed label"))) -> Agreed label | F7: =IF(D7<>B7,"Yes","") | G7: =IF(D7<>C7,"Yes","")
A8: 8044 | B8: =INDEX('Labeler 1'!$C$2:$C$181,MATCH(A8,'Labeler 1'!$A$2:$A$181,0)) -> Consumer loan | C8: =INDEX('Labeler 2'!$C$2:$C$181,MATCH(A8,'Labeler 2'!$A$2:$A$181,0)) -> Consumer loan | D8: =IF(COUNTIF('Resolution Log'!$A$5:$A$24,A8)>0,INDEX('Resolution Log'!$G$5:$G$24,MATCH(A8,'Resolution Log'!$A$5:$A$24,0)),IF(COUNTIFS('Consistency Check'!$A$5:$A$99,A8,'Consistency Check'!$D$5:$D$99,"No")>0,INDEX('Consistency Check'!$E$5:$E$99,MATCH(A8,'Consistency Check'!$A$5:$A$99,0)),C8)) -> Consumer loan | E8: =IF(COUNTIF('Resolution Log'!$A$5:$A$24,A8)>0,"Resolution Log (disagreement)",IF(COUNTIFS('Consistency Check'!$A$5:$A$99,A8,'Consistency Check'!$D$5:$D$99,"No")>0,"Consistency Check (agreed label changed)",IF(COUNTIF('Consistency Check'!$A$5:$A$99,A8)>0,"Consistency Check (agreed label confirmed)","Agreed label"))) -> Consistency Check (agreed label confirmed) | F8: =IF(D8<>B8,"Yes","") | G8: =IF(D8<>C8,"Yes","")
A9: 8050 | B9: =INDEX('Labeler 1'!$C$2:$C$181,MATCH(A9,'Labeler 1'!$A$2:$A$181,0)) -> Debt collection | C9: =INDEX('Labeler 2'!$C$2:$C$181,MATCH(A9,'Labeler 2'!$A$2:$A$181,0)) -> Debt collection | D9: =IF(COUNTIF('Resolution Log'!$A$5:$A$24,A9)>0,INDEX('Resolution Log'!$G$5:$G$24,MATCH(A9,'Resolution Log'!$A$5:$A$24,0)),IF(COUNTIFS('Consistency Check'!$A$5:$A$99,A9,'Consistency Check'!$D$5:$D$99,"No")>0,INDEX('Consistency Check'!$E$5:$E$99,MATCH(A9,'Consistency Check'!$A$5:$A$99,0)),C9)) -> Debt collection | E9: =IF(COUNTIF('Resolution Log'!$A$5:$A$24,A9)>0,"Resolution Log (disagreement)",IF(COUNTIFS('Consistency Check'!$A$5:$A$99,A9,'Consistency Check'!$D$5:$D$99,"No")>0,"Consistency Check (agreed label changed)",IF(COUNTIF('Consistency Check'!$A$5:$A$99,A9)>0,"Consistency Check (agreed label confirmed)","Agreed label"))) -> Agreed label | F9: =IF(D9<>B9,"Yes","") | G9: =IF(D9<>C9,"Yes","")
A10: 8053 | B10: =INDEX('Labeler 1'!$C$2:$C$181,MATCH(A10,'Labeler 1'!$A$2:$A$181,0)) -> Credit reporting | C10: =INDEX('Labeler 2'!$C$2:$C$181,MATCH(A10,'Labeler 2'!$A$2:$A$181,0)) -> Credit reporting | D10: =IF(COUNTIF('Resolution Log'!$A$5:$A$24,A10)>0,INDEX('Resolution Log'!$G$5:$G$24,MATCH(A10,'Resolution Log'!$A$5:$A$24,0)),IF(COUNTIFS('Consistency Check'!$A$5:$A$99,A10,'Consistency Check'!$D$5:$D$99,"No")>0,INDEX('Consistency Check'!$E$5:$E$99,MATCH(A10,'Consistency Check'!$A$5:$A$99,0)),C10)) -> Credit reporting | E10: =IF(COUNTIF('Resolution Log'!$A$5:$A$24,A10)>0,"Resolution Log (disagreement)",IF(COUNTIFS('Consistency Check'!$A$5:$A$99,A10,'Consistency Check'!$D$5:$D$99,"No")>0,"Consistency Check (agreed label changed)",IF(COUNTIF('Consistency Check'!$A$5:$A$99,A10)>0,"Consistency Check (agreed label confirmed)","Agreed label"))) -> Agreed label | F10: =IF(D10<>B10,"Yes","") | G10: =IF(D10<>C10,"Yes","")
A11: 8060 | B11: =INDEX('Labeler 1'!$C$2:$C$181,MATCH(A11,'Labeler 1'!$A$2:$A$181,0)) -> Credit reporting | C11: =INDEX('Labeler 2'!$C$2:$C$181,MATCH(A11,'Labeler 2'!$A$2:$A$181,0)) -> Credit reporting | D11: =IF(COUNTIF('Resolution Log'!$A$5:$A$24,A11)>0,INDEX('Resolution Log'!$G$5:$G$24,MATCH(A11,'Resolution Log'!$A$5:$A$24,0)),IF(COUNTIFS('Consistency Check'!$A$5:$A$99,A11,'Consistency Check'!$D$5:$D$99,"No")>0,INDEX('Consistency Check'!$E$5:$E$99,MATCH(A11,'Consistency Check'!$A$5:$A$99,0)),C11)) -> Credit reporting | E11: =IF(COUNTIF('Resolution Log'!$A$5:$A$24,A11)>0,"Resolution Log (disagreement)",IF(COUNTIFS('Consistency Check'!$A$5:$A$99,A11,'Consistency Check'!$D$5:$D$99,"No")>0,"Consistency Check (agreed label changed)",IF(COUNTIF('Consistency Check'!$A$5:$A$99,A11)>0,"Consistency Check (agreed label confirmed)","Agreed label"))) -> Agreed label | F11: =IF(D11<>B11,"Yes","") | G11: =IF(D11<>C11,"Yes","")
A12: 8062 | B12: =INDEX('Labeler 1'!$C$2:$C$181,MATCH(A12,'Labeler 1'!$A$2:$A$181,0)) -> Credit reporting | C12: =INDEX('Labeler 2'!$C$2:$C$181,MATCH(A12,'Labeler 2'!$A$2:$A$181,0)) -> Credit reporting | D12: =IF(COUNTIF('Resolution Log'!$A$5:$A$24,A12)>0,INDEX('Resolution Log'!$G$5:$G$24,MATCH(A12,'Resolution Log'!$A$5:$A$24,0)),IF(COUNTIFS('Consistency Check'!$A$5:$A$99,A12,'Consistency Check'!$D$5:$D$99,"No")>0,INDEX('Consistency Check'!$E$5:$E$99,MATCH(A12,'Consistency Check'!$A$5:$A$99,0)),C12)) -> Credit reporting | E12: =IF(COUNTIF('Resolution Log'!$A$5:$A$24,A12)>0,"Resolution Log (disagreement)",IF(COUNTIFS('Consistency Check'!$A$5:$A$99,A12,'Consistency Check'!$D$5:$D$99,"No")>0,"Consistency Check (agreed label changed)",IF(COUNTIF('Consistency Check'!$A$5:$A$99,A12)>0,"Consistency Check (agreed label confirmed)","Agreed label"))) -> Agreed label | F12: =IF(D12<>B12,"Yes","") | G12: =IF(D12<>C12,"Yes","")
A13: 8071 | B13: =INDEX('Labeler 1'!$C$2:$C$181,MATCH(A13,'Labeler 1'!$A$2:$A$181,0)) -> Credit reporting | C13: =INDEX('Labeler 2'!$C$2:$C$181,MATCH(A13,'Labeler 2'!$A$2:$A$181,0)) -> Credit reporting | D13: =IF(COUNTIF('Resolution Log'!$A$5:$A$24,A13)>0,INDEX('Resolution Log'!$G$5:$G$24,MATCH(A13,'Resolution Log'!$A$5:$A$24,0)),IF(COUNTIFS('Consistency Check'!$A$5:$A$99,A13,'Consistency Check'!$D$5:$D$99,"No")>0,INDEX('Consistency Check'!$E$5:$E$99,MATCH(A13,'Consistency Check'!$A$5:$A$99,0)),C13)) -> Credit reporting | E13: =IF(COUNTIF('Resolution Log'!$A$5:$A$24,A13)>0,"Resolution Log (disagreement)",IF(COUNTIFS('Consistency Check'!$A$5:$A$99,A13,'Consistency Check'!$D$5:$D$99,"No")>0,"Consistency Check (agreed label changed)",IF(COUNTIF('Consistency Check'!$A$5:$A$99,A13)>0,"Consistency Check (agreed label confirmed)","Agreed label"))) -> Agreed label | F13: =IF(D13<>B13,"Yes","") | G13: =IF(D13<>C13,"Yes","")
A14: 8074 | B14: =INDEX('Labeler 1'!$C$2:$C$181,MATCH(A14,'Labeler 1'!$A$2:$A$181,0)) -> Credit reporting | C14: =INDEX('Labeler 2'!$C$2:$C$181,MATCH(A14,'Labeler 2'!$A$2:$A$181,0)) -> Credit reporting | D14: =IF(COUNTIF('Resolution Log'!$A$5:$A$24,A14)>0,INDEX('Resolution Log'!$G$5:$G$24,MATCH(A14,'Resolution Log'!$A$5:$A$24,0)),IF(COUNTIFS('Consistency Check'!$A$5:$A$99,A14,'Consistency Check'!$D$5:$D$99,"No")>0,INDEX('Consistency Check'!$E$5:$E$99,MATCH(A14,'Consistency Check'!$A$5:$A$99,0)),C14)) -> Credit reporting | E14: =IF(COUNTIF('Resolution Log'!$A$5:$A$24,A14)>0,"Resolution Log (disagreement)",IF(COUNTIFS('Consistency Check'!$A$5:$A$99,A14,'Consistency Check'!$D$5:$D$99,"No")>0,"Consistency Check (agreed label changed)",IF(COUNTIF('Consistency Check'!$A$5:$A$99,A14)>0,"Consistency Check (agreed label confirmed)","Agreed label"))) -> Agreed label | F14: =IF(D14<>B14,"Yes","") | G14: =IF(D14<>C14,"Yes","")
A15: 8094 | B15: =INDEX('Labeler 1'!$C$2:$C$181,MATCH(A15,'Labeler 1'!$A$2:$A$181,0)) -> Money transfer or service | C15: =INDEX('Labeler 2'!$C$2:$C$181,MATCH(A15,'Labeler 2'!$A$2:$A$181,0)) -> Money transfer or service | D15: =IF(COUNTIF('Resolution Log'!$A$5:$A$24,A15)>0,INDEX('Resolution Log'!$G$5:$G$24,MATCH(A15,'Resolution Log'!$A$5:$A$24,0)),IF(COUNTIFS('Consistency Check'!$A$5:$A$99,A15,'Consistency Check'!$D$5:$D$99,"No")>0,INDEX('Consistency Check'!$E$5:$E$99,MATCH(A15,'Consistency Check'!$A$5:$A$99,0)),C15)) -> Money transfer or service | E15: =IF(COUNTIF('Resolution Log'!$A$5:$A$24,A15)>0,"Resolution Log (disagreement)",IF(COUNTIFS('Consistency Check'!$A$5:$A$99,A15,'Consistency Check'!$D$5:$D$99,"No")>0,"Consistency Check (agreed label changed)",IF(COUNTIF('Consistency Check'!$A$5:$A$99,A15)>0,"Consistency Check (agreed label confirmed)","Agreed label"))) -> Agreed label | F15: =IF(D15<>B15,"Yes","") | G15: =IF(D15<>C15,"Yes","")
A16: 8095 | B16: =INDEX('Labeler 1'!$C$2:$C$181,MATCH(A16,'Labeler 1'!$A$2:$A$181,0)) -> Money transfer or service | C16: =INDEX('Labeler 2'!$C$2:$C$181,MATCH(A16,'Labeler 2'!$A$2:$A$181,0)) -> Bank account or service | D16: =IF(COUNTIF('Resolution Log'!$A$5:$A$24,A16)>0,INDEX('Resolution Log'!$G$5:$G$24,MATCH(A16,'Resolution Log'!$A$5:$A$24,0)),IF(COUNTIFS('Consistency Check'!$A$5:$A$99,A16,'Consistency Check'!$D$5:$D$99,"No")>0,INDEX('Consistency Check'!$E$5:$E$99,MATCH(A16,'Consistency Check'!$A$5:$A$99,0)),C16)) -> Bank account or service | E16: =IF(COUNTIF('Resolution Log'!$A$5:$A$24,A16)>0,"Resolution Log (disagreement)",IF(COUNTIFS('Consistency Check'!$A$5:$A$99,A16,'Consistency Check'!$D$5:$D$99,"No")>0,"Consistency Check (agreed label changed)",IF(COUNTIF('Consistency Check'!$A$5:$A$99,A16)>0,"Consistency Check (agreed label confirmed)","Agreed label"))) -> Resolution Log (disagreement) | F16: =IF(D16<>B16,"Yes","") -> Yes | G16: =IF(D16<>C16,"Yes","")
... A184: 8999 | B184: =INDEX('Labeler 1'!$C$2:$C$181,MATCH(A184,'Labeler 1'!$A$2:$A$181,0)) -> Consumer loan | C184: =INDEX('Labeler 2'!$C$2:$C$181,MATCH(A184,'Labeler 2'!$A$2:$A$181,0)) -> Consumer loan | D184: =IF(COUNTIF('Resolution Log'!$A$5:$A$24,A184)>0,INDEX('Resolution Log'!$G$5:$G$24,MATCH(A184,'Resolution Log'!$A$5:$A$24,0)),IF(COUNTIFS('Consistency Check'!$A$5:$A$99,A184,'Consistency Check'!$D$5:$D$99,"No")>0,INDEX('Consistency Check'!$E$5:$E$99,MATCH(A184,'Consistency Check'!$A$5:$A$99,0)),C184)) -> Consumer loan | E184: =IF(COUNTIF('Resolution Log'!$A$5:$A$24,A184)>0,"Resolution Log (disagreement)",IF(COUNTIFS('Consistency Check'!$A$5:$A$99,A184,'Consistency Check'!$D$5:$D$99,"No")>0,"Consistency Check (agreed label changed)",IF(COUNTIF('Consistency Check'!$A$5:$A$99,A184)>0,"Consistency Check (agreed label confirmed)","Agreed label"))) -> Consistency Check (agreed label confirmed) | F184: =IF(D184<>B184,"Yes","") | G184: =IF(D184<>C184,"Yes","")
A186: Summary
A187: Rows | D187: =COUNTA(A5:A184) -> 180
A188: Final labels that are blank or invalid (should be 0) | D188: =COUNTA(A5:A184)-SUMPRODUCT(COUNTIF(D5:D184,{"Credit reporting","Debt collection","Mortgage","Credit card","Bank account or service","Consumer loan","Money transfer or service"})) -> 0
A189: Source: Resolution Log (disagreement) | D189: =COUNTIF(E5:E184,"Resolution Log*") -> 20
A190: Source: agreed label changed | D190: =COUNTIF(E5:E184,"*changed*") -> 2
A191: Source: agreed label confirmed on Consistency Check | D191: =COUNTIF(E5:E184,"*confirmed*") -> 42
A192: Source: agreed label, not affected by any rule change | D192: =COUNTIF(E5:E184,"Agreed label") -> 116
A193: Final differs from Labeler 1 | D193: =COUNTIF(F5:F184,"Yes") -> 15
A194: Final differs from Labeler 2 | D194: =COUNTIF(G5:G184,"Yes") -> 10
A195: Final differs from both labellers | D195: =COUNTIFS(F5:F184,"Yes",G5:G184,"Yes") -> 3
A197: Final label distribution
A198: Credit reporting | D198: =COUNTIF(D5:D184,A198) -> 53 | E198: =D198/D187 -> 0.29444444
A199: Debt collection | D199: =COUNTIF(D5:D184,A199) -> 16 | E199: =D199/D187 -> 0.088888889
A200: Mortgage | D200: =COUNTIF(D5:D184,A200) -> 26 | E200: =D200/D187 -> 0.14444444
A201: Credit card | D201: =COUNTIF(D5:D184,A201) -> 20 | E201: =D201/D187 -> 0.11111111
A202: Bank account or service | D202: =COUNTIF(D5:D184,A202) -> 23 | E202: =D202/D187 -> 0.12777778
A203: Consumer loan | D203: =COUNTIF(D5:D184,A203) -> 19 | E203: =D203/D187 -> 0.10555556
A204: Money transfer or service | D204: =COUNTIF(D5:D184,A204) -> 23 | E204: =D204/D187 -> 0.12777778

Sheet Protocol
A1: ICT3113 Assignment 1 -- Team 8 Labelling Protocol (V10)
A2: Golden test set: 180 tickets from rows 8000-8999, stratified proportional to raw category mix. Labelled independently by 2 team members (Hakim & Glenn), no conferring, then reconciled.
A4: Category | B4: Core scope | C4: Edge-case rule
A5: Credit reporting | B5: Errors, disputes, or investigations about what's ON a credit report/file itself (accuracy, unauthorized accounts, bureau disputes) | C5: Classify by the MAIN OUTCOME the ticket asks for, not the laws it cites. If the main demand is removing or correcting an entry on the credit report -> here, even if validation or the FDCPA is cited as the reason. When a ticket asks for both, go with the request that has actual events behind it. (rev 4)
A6: Debt collection | B6: Collection conduct by a collection agency, debt buyer, attorney, or the creditor itself (calls, harassment, threats, lawsuits, garnishment, wrong amount, validation requests) -> here. A creditor's fees, terms or account servicing -> that product's category. (rev 10) | C6: If the main demand is validation or verification of the debt itself (e.g. an itemized validation request to a collector, or disputing that the debt is owed) -> here, even if deletion from credit reports is requested as the consequence of failed validation. (rev 4)
A7: Mortgage | B7: Origination, servicing, PMI, refinancing, foreclosure on a home loan | C7: If reporting accuracy of the mortgage account is the actual complaint -> Credit reporting. Foreclosure framed as collector misconduct (e.g. false representations, improper seizure of property) -> Debt collection; problems with the foreclosure process itself (e.g. notices, loss mitigation, servicer handling) -> stays Mortgage. (rev 5)
A8: Credit card | B8: Card fees, charges, disputes, closures, rewards, APR issues | C8: Store-branded credit cards (a card used to finance purchases at a particular store, chain or dealer) -> here. (rev 7)
A9: Bank account or service | B9: Checking and savings accounts, including online banks (e.g. Chime, Marcus), and their debit cards: deposits, holds, checks, fees, closures, unauthorized access or charges (rev 3). | C9: If a real loan's payments or funds route through a bank account (e.g. loan payments debited from checking) -> Consumer loan, unless the account-level action (freeze/closure) is the actual complaint. If no loan exists (e.g. a company the customer never borrowed from takes money), the Fraud and unrecognised accounts rule applies. (rev 10) Prepaid cards fit no category -> force-fit here: the card holds the customer's own funds, like an account. (rev 7)
A10: Consumer loan | B10: Personal loans, auto loans, student loans, and their servicing | C10: A loan whose type is not named -> Consumer loan, unless a mortgage-specific term appears (e.g. escrow, PMI, foreclosure, refinance, home or property) -> Mortgage. "Servicer" alone is not a mortgage signal: mortgages, student loans and auto loans all have servicers. (rev 6) Buy-now-pay-later and point-of-sale instalment financing -> here when the complaint is about the financing itself; if the complaint is about payments a payment app actually processed, rev 3 applies. (rev 7)
A11: Money transfer or service | B11: Payment apps, digital wallets, crypto platforms, and transfer services (e.g. PayPal, Cash App, Venmo, Zelle, Coinbase, wires the customer sends, remittances such as Western Union) (rev 3). | C11: Categorize by PRODUCT, not by what went wrong: a lock, fraud, fee, or stuck payment on a payment app, wallet, or crypto platform stays here; the same problem on a bank deposit account -> Bank account or service (rev 3).
A13: General Rules
A14: Fits two categories: | B14: Classify by the financial PRODUCT that is the substance of the complaint, not the mechanism used to raise it. Use the edge-case rules above to break ties.
A15: Fits none well: | B15: Force-fit to the closest of the 7 (the service can only output one of these 7), and write a short reason in the Flag/Notes column. Do not leave the category blank.
A16: Fraud and unrecognised accounts: | B16: If the grievance is with a credit bureau, or the main demand is removal from the credit report -> Credit reporting. If the grievance is with the company holding the account (how the lender, card issuer or bank handles the fraud) -> that account's product category, even if it also appears on the credit report. Money taken from the customer's own account without authorization by someone they have no account or agreement with (a stranger, an impostor, an unknown company) -> the customer's own account decides the category (rev 3); the payee's line of business and the payment method (card, ACH, wire) do not. If the customer has an account or agreement with the company that took the money (a lender, seller, or payment app they used), that relationship decides. (rev 8)
A17: Product not stated: | B17: When the product is not stated: a dispute over a purchase from a merchant (non-delivery, overcharge, return) -> Credit card; an action by a bank on the account itself (closure, freeze) -> Bank account. This is a default for missing information, not something the text proves; do not infer the product from what a provider is known for. (rev 9)
A18: Order of application: | B18: The specific rules (category edge-case rules, Fraud and unrecognised accounts, Product not stated) take precedence over Fits two categories; Fits none well is the last resort. (rev 10)
A19: Revision log | B19: See the Revision Log tab.
A20: Heuristic scan results (run on all 180 candidates)
A21: 25 of 180 rows (~14%) flagged before labelling as likely edge cases (26 flags; one row, 8644, carried two) -- see heuristic_flag column on Labeler tabs. Pre-labelling notes; outcomes are recorded in the Revision Log.
A22: 11 rows: loan-servicer complaint with no product named (mortgage vs consumer loan). Resolved by rev 6.
A23: 7 rows: raw label Credit card but no card-related language -- check for raw mislabeling.
A24: 6 rows: both debt-collection and credit-reporting language present. Resolved by rev 4.
A25: 2 rows: loan and bank-account language both present.

Sheet Labeler 1
A1: row_id | B1: narrative | C1: your_category | D1: flag_note (if forced/hard fit/general comments)
A2: 8022 | B2: I applied for a bank account with XXXX on XXXX XXXX and was declined stating there were discrepancies on my XXXX report. I knew that had to be an error because i filed for bankruptcy and every creditor was ordered by the judge to CEASE AND DESIST. I filed chapter XXXX bankruptcy with case XXXX FL on XX/XX/17 and the case was discharged in XX/XX/2017. However, XXXX XXXX is STILL REPORTING EVEN AFTER MY BANKRUPTCY. Each creditor is subject to up to {$1000.00} fine for violation of fair credit reporting act. Chapter XXXX bankruptcy discharges all debt! | C2: Credit reporting
A3: 8024 | B3: I fell victim to a multilayered scam operation orchestrated by XXXX ( XXXX ) ( the Company ) with the design, development, manufacturing, promoting, marketing, distributing, labeling, and/or sale of illegal and outright fraudulent investment services, all of which aim at contributing to the goal of robbing and defrauding clients through a predetermined cycle of client losses to gains in the equivalent of XXXX USD which was transferred from my wallet utilizing Coinbases services. | C3: Money transfer or service
A4: 8033 | B4: I have been a longstanding customer with Chase Bank, maintaining multiple credit card accounts with them over a period of several years. I have always managed my accounts responsibly, making timely payments and adhering to all the terms and conditions. To my knowledge, I have not violated any rules or engaged in any behavior that would warrant account closure. Recently, I discovered that Chase had closed all of my credit card accounts without prior notice or explanation. I received no warning or notification regarding any issues with my accounts. Upon noticing the closures, I immediately contacted Chase customer service to inquire about the reason behind their decision. Despite multiple attempts and speaking with several representatives, Chase refused to provide any specific reason for the closures. I was told that they were unable to disclose why the accounts were closed and that the decision was final. I was not given any opportunity to appeal or resolve any potential issue that may have prompted this action. This sudden and unexplained closure of my credit card accounts has caused me significant inconvenience and concern. It has impacted my credit utilization ratio, which may negatively affect my credit score, and I am now left without access to credit that I previously relied on for regular financial activities. I believe that as a consumer in good standing, I am entitled to a clear explanation for the closure of my accounts. The lack of transparency and unwillingness to provide any justification is deeply troubling and potentially unfair. I am requesting that the CFPB investigate this matter and help facilitate a response from Chase that provides a clear and detailed explanation for their actions. | C4: Credit card
A5: 8044 | B5: My husband and I open a personal loan through OneMain. The company was originally named SpringLeaf. The loan was paid in full XXXX XXXX, 2017. I tried to obtain an letter from the company stating this loan was paid in full ; so I could provide it to the three credit bureaus ; but, was unsuccessful. Attached will be a summary printout from the local office and a statement printout providing {$0.00} balance. Even though these statements are acceptable to me ; there are not acceptable for the three credit reporting bureaus. Would you please assist me with this matter? Thank you | C5: Consumer loan | D5: The product is explicitly a personal loan; the request for payoff documentation is incidental to the loan itself, so Consumer loan applies.
A6: 8050 | B6: Cypress Collections Professional Collection Agency XX/XX/XXXX XXXX XXXX XXXX XXXX, CA XXXX Re : Reference # XXXX Client # XXXX Thank you for your inquiry. I do in fact dispute the claim of {$120.00} plus the additional interest that was erroneously billed to me and certainly, your threats to damage my credit worthiness. I am a Veteran under the care of the Veterans Administration at XXXX XXXX. I have communicated with Doctors on Duty and have told them that their claim needs to be filed with the Veterans Administration. I also told Doctors on Duty that I would talk to the VA regarding the erroneous billing for my approved office visit. I talked to my primary care doctor at the VA and was told that there is a record of an authorized request for medical service on XX/XX/XXXX. Initially I told this to Doctors on Duty bookeeper. I clearly told the Doctors on Duty staff that the VA sent me and that I needed to be evaluated for XXXX because of XXXX XXXX and that I was a veteran. The reason for this going to collection is clearly not my doing. It is in fact Doctors on Duty responsibility to bill the VA as per their contract ( a requirement that they did not do ) Embroiling me in their mishap with a threat of affecting my credit worthiness is disturbing at best. I have contacted the Community Provider division of VA and have filed an Adverse Credit Report - XXXX. Cypress Collection as well as Doctors on Duty have been notified to cease and desist their illegal claim. If in fact my credit worthiness is affected, I will sue for defamation of character and elder abuse of an ailing veteran. I am willing to pursue a course of action against both Doctors on Duty and Cypress if this persists any longer. I defended my country with dignity and courage and expect respect and thanks for my service, rather than being threatened and abused by Doctors on Duty and Cypress Collections. Thank You XXXX cc : FTC www.ftc.gov cc : Senator XXXX XXXX | C6: Debt collection | D6: Both collection and reporting language appear, but the complaint centers on the collector's billing/threats and cease-and-desist demand; Debt collection applies.
A7: 8053 | B7: I was shocked when I reviewed my credit report and found late payment on the dates below : XX/XX/2018- 30 DAYS LATE I am not sure how this happened, I believe that I had made my payments to you when I received my statements. My only thought is that my monthly statement did not get to me. | C7: Credit reporting | D7: No card is named; the complaint is explicitly about a late-payment entry on the credit report, so Credit reporting applies.
A8: 8060 | B8: I've recently received a copy of my credit report and noticed several inaccuracies and unauthorized accounts/information reporting to my credit report. These remarks have been detrimental to my life and credit health. CAPIO PARTNERS LLC {$3100.00} XX/XX/year> | C8: Credit reporting
A9: 8062 | B9: I am submitting this complaint regarding Credit Karmas refusal to update my legal name on their platform, despite my repeated efforts and full compliance with their documentation requirements. I legally changed my name and have already updated it with the XXXX XXXX XXXX and on my government-issued ID. I contacted Credit Karma to request that they update my account to reflect my correct legal name. As requested, I submitted a copy of my government-issued ID and Social Security card , both showing my current legal name. Despite providing this documentation, Credit Karma has refused to update my account. Their support team has not given a clear or valid reason for this refusal, nor have they offered any alternative solution. This failure to update my name has caused confusion and concern, especially as Credit Karma continues to pull and report credit information under a name that is no longer legally mine. I am concerned that this may impact the accuracy of my credit file and hinder my ability to manage my financial accounts effectively. I believe I have made every reasonable effort to work with Credit Karma, and I am now requesting assistance from the CFPB to resolve this matter. I am seeking that Credit Karma update my name in their system in accordance with the legal documentation I have provided and that they ensure all associated credit reporting is accurate. | C9: Credit reporting
A10: 8071 | B10: Upon termination of my lease in XXXX I was assessed a disposition fee above the contractual obligation. In investigating this fee I had discovered that XXXX XXXX was charging for hail damage to the vehicle. This vehicle never experienced a hail storm while in my possession. The process of contacting XXXX XXXX XXXX XXXX and disputing the charge took costly time. Once the determination was made by a XXXX representative that I was indeed not responsible for any additional charges, as there was no hail damage, I immediately paid the remaining disposition fee. I had never been late in a vehicle payment to XXXX or any other automotive debtor. Because of the time it took XXXX XXXX to investigate and correct this charge I was outside of my 30 day payment window. They they reported me to the 3 bureaus as having a late payment. I sent my formal request to have the negative marks removed from my credit report at the 3 bureaus ; XXXX, XXXX, and XXXX. I submit this request on authority from the representatives at XXXX. I included a brief statement on what had happened and a copy of my credit report. On XX/XX/XXXX I received a letter from XXXX XXXX saying their reporting was correct. I called on XX/XX/XXXX to take further action. At this point I was informed I could make another formal dispute but could not actually speak with anyone who makes the decisions. A customer service rep by the name of XXXX and his supervisor XXXX were quite unwilling to help. I just want the negative mark removed from my credit. I am currently not obligated with any further debt to XXXX XXXX. | C10: Credit reporting
A11: 8074 | B11: I am writing to request an investigation of the following information that appears on my Early Warning Systems consumer report, which I believe to be fraudulent. In accordance with the Fair Credit Reporting Act, I assert that the list of accounts below has violated my federally protected consumer rights to privacy and confidentiality under 15 USC 1681. These items listed above have violated my rights as outlined in 15 U.S.C. 1681, Section 602 A, which grants me the right to privacy. 15 U.S.C. 1681, Section 604 A, Section 2 also states that a consumer reporting agency can not furnish an account without my written instructions. Furthermore, 15 U.S.C. 1681c ( a ) ( 5 ) stipulates that no consumer reporting agency may include any adverse items on a consumer report if they predate the report by more than seven years. Additionally, 15 U.S.C. 1681s-2 ( a ) ( 1 ) specifies that no information can be furnished to a consumer reporting agency if the person knows, or has reasonable cause to believe, that the information is inaccurate. I have NEVER opened or used the following account numbers, and I request that all information related to these accounts be removed immediately : Bank : XXXX XXXX Incident Date : XX/XX/year> Contribution Ref # : XXXX Account # : XXXX ABA Number # : XXXX Additionally, I do not recognize the following inquiries that appear on my report. I am a victim of identity theft, and I do not recognize the following inquiries. I request that the following inquiries be removed from my Early Warning Services consumer report immediately : | C11: Credit reporting
A12: 8094 | B12: On XX/XX/XXXX an online transaction was made through our banking institution Wells Fargo via XXXX in the amount of {$230.00}. XX/XX/XXXX XXXX TO XXXX XXXX ON XX/XX/XXXX REF # XXXX {$230.00}. The product/service was not received. Contacted Wells Fargo and a claim was filed # XXXX. We would like our money back. This was fraudulent act committed ; Wells Fargo should back all transactions on their website and in good faith refund the customer. We were told most likely we would not be getting our funds back. Please assist in obtaining our {$230.00} back. Thanks. | C12: Money transfer or service
A13: 8095 | B13: On XX/XX/XXXX/XX/XX/XXXX my debit card was stolen while on a work trip in XXXX, New York In addition it was my contention that the thief was able to get my PIN. That thief, used the card throughout the XXXX XXXX XXXX area, charging up almost {$3000.00} dollars at 30 various different drug stores over a 3 hour period, making cash back purchases in small increments on average of {$50.00} dollars. I reported the fraudulent charges to the bank as soon as I became aware, as did my wife who is joint on the account. I filed a police report in XXXX XXXX XXXX and XXXX XXXX, CA, my place of residence. Upon review the bank rescinded the credits to my account and stated their judgement was based upon inconsistencies with my and my wife 's statements. As i mentioned to the back, I was not aware of how it was stolen, but merely giving them suggestions on who might have been the perpetrator. The bank investigators did n't not put forward a good faith effort to follow up on this claim, nor did the bank hold up their fiduciary responsibility to protect my debit card from this clear fraud while it was happening. Furthermore, while I still have an active police investigation, the bank has already rendered judgement. This matter will be resolved in civil court if I ca n't get the protection of the Bank in regards to my FDIC protected money. I wish to report the bank, the claims department and its management for gross negligence in this matter and I hope the CFPB can help me gain protection from a banks disregard for its primarily responsibility to protect my money | C13: Money transfer or service
A14: 8096 | B14: An unauthorized transaction was made on my Chime XXXX XXXX account on XX/XX/year> in the amount of {$1400.00} at XXXX XXXX. I transferred funds to my account to set aside for a moving fund. I filed a dispute with Chime on XX/XX/XXXX they then denied my claim the following day without proper investigation. An appeal or rebuttal was filed on XX/XX/XXXX at which point I also provided a written statement and a statement from the business stating the charge was unauthorized. That rebuttal was also denied despite submitting substantial information. I tried calling police but because I was unsure where I misplaced my credit card they were unwilling to file a dispute. It has been now almost XXXX months of me fighting the bank and nothing has been returned to me and this issue has yet to be resolved. | C14: Money transfer or service
A15: 8097 | B15: I have notified Experian, XXXX and XXXX several times regarding the XXXX XXXX account. XXXX XXXX is refusing to discuss collection for XXXX account or accept any payments from me stating they are no longer handling account it is with a 3rd party. The is no other company reporting this account to my credit report, only XXXX XXXX. I have attempted several times to resolve this account with XXXX XXXX with the latest being today XX/XX/2021 at XXXX eastern, I spoke with XXXX whom once again refuses to discuss account, accept payment or even send a current dated bill for the balance owed. I have recorded conversations of XXXX XXXX refusals. I have filed several disputes advising Experian, XXXX and XXXX of the issues with XXXX XXXX and the recorded conversations with contact information to reach me to hear them. All 3 continue to close my disputes stating they verified account details without investigating the issue Im disputing. XXXX XXXX should not be allowed to remain on my credit report if they are refusing to discuss account, accept payment for account or even send me a current bill for account. At this point Im ready to get a lawyer and sue Experian, XXXX, XXXX and XXXX XXXX because Ive tried for several months to resolve this myself to no avail. | C15: Credit reporting
A16: 8098 | B16: I am submitting this complaint due to a judgment and wage garnishment related to a charged-off XXXX account. I was never properly served with notice of the original lawsuit and only became aware of the judgment after receiving notice that my wages would be garnished. I did not live at the address sworn to be served at. I have attached my lease for the time frame in question. I filed a Motion to Strike the judgment on the grounds of improper service, but it was denied. The debt collector has not provided a valid affidavit or proof of service that complies with state law requirements. I believe this violated my due process rights. Additionally, I never received a proper debt validation or breakdown of the amount allegedly owed. The debt was originally charged off by XXXX, and I do not have confirmation that the current party attempting to collect has the legal right to do so. I am requesting the following from the CFPB : An investigation into whether proper service of process was completed before the judgment was granted. Confirmation that the entity pursuing the garnishment is authorized to collect on this debt. Full validation of the alleged debt, including the original contract, chain of assignment, and accounting of charges. I believe this judgment and garnishment may have been obtained unlawfully and am requesting assistance in having it vacated if violations occurred. Thank you for your attention to this matter. | C16: Debt collection
A17: 8106 | B17: My mortgage loan originated XX/XX/XXXX. In XXXX, I applied for a home made affordable loan modification but was denied. Wells Fargo informed me that I could do a short sale. My realtor submitted several offers to them for a short sale and they refused them and proceeded to foreclose on the property in XX/XX/XXXX. On XX/XX/XXXX, I contacted Wells Fargo 's Enterprise Complaints Mgmt Office letting them know that I felt my home had been wrongfully foreclosed and was given a case number and assigned a representative. XXXX XXXX is my Case SpecialistXXXX XXXX XXXXXXXX. I have received four different letters stating they need more time to finalize their research. I feel they are are not taking the situation seriously. I was told that another letter is in the mail stating that they should complete their work by XX/XX/XXXX. That will be two months from the date that I reached out to them. | C17: Mortgage
A18: 8108 | B18: I last spoke with a supervisor ( XXXX ) on XXXX after receiving the last response from a Citibank Representative on my recent complaint with CFPB. Although, I did not inquire about " settling '' the account I was not given any options on how to resolve the balance either. Currently, the principal balance according to XXXX is {$590.00} with {$170.00} ( late fees of {$25.00} per month ) plus any interest. Prior to the conversation with XXXX, a conversation ( early XXXX ) with a representative in the loan department stated that " for two payments ( XXXX and XXXX ) no interest would be charged and the account would be deferred. '' I would not need to make any payments. But, I made a payment in XXXX in the amount of {$250.00} ( {$220.00} is the minimum payment ). XXXX refused to provide any options on how to resolve the matter. I asked about waiving a few fees, to which were immediately dismissed by saying '' we can't do that because you were consistently late. '' Which I felt was extremely offensive, I felt like a criminal in that moment. In XXXX of last year, I lost my job which put me behind in payments. But I paid what I could. Now I am a product of the Pandemic, but I am still paying trying to resolve this responsibility. I was so angry by her statement that I responded back stating " I could easily let the account go and not pay anything! '' My experience with Citibank has been an extremely horrible ordeal. It is unfortunate that I stayed this long, over 10 years. | C18: Consumer loan | D18: Loan type is not named; using Consumer loan as the standing generic-loan tie-break.
A19: 8118 | B19: I am filling a complaint against Cash App ( Block INC. ) due to inadequate customer service and unfair practices, which violate the Consumer Financial Protection Act. Specifically, Cash App failed to take timely and effective measures to prevent and address fraud on their platform, leaving my account vulnerable and unprotected. Furthermore, their dispute resolution process was unfair and deceptive, as they did not comply with Electronic Fund Transfer Act and Regulation E. These actions have caused significant inconvenience and financial loss and i seek appropriate redress for these violations | C19: Money transfer or service
A20: 8122 | B20: I am filing this complaint regarding a medical collection account being reported on my consumer credit reports by Aargon Agency , Inc . This account is inaccurate, unlawfully reported, and should be immediately deleted for the reasons outlined below. First, I never authorized the original medical provider or any third party to disclose my protected health information ( PHI ) to this collection agency for the purpose of credit reporting. The reporting and furnishing of this account necessarily involves the disclosure of sensitive medical information, which I did not consent to. This appears to be a violation of the Health Insurance Portability and Accountability Act ( HIPAA ) and its privacy protections regarding unauthorized disclosure of medical information. Second, this account has been reported to the consumer reporting agencies without proper validation and without a permissible purpose, in violation of the Fair Credit Reporting Act ( 15 U.S.C. 1681 et seq. ). I dispute the accuracy, ownership, and legal authority of this collection account. The furnisher has failed to demonstrate that it has the legal right to report this alleged debt or that the information being reported is complete and accurate. Additionally, medical collections are subject to heightened accuracy and privacy requirements. The continued reporting of this account is causing ongoing harm to my credit profile and financial well-being. I am requesting that the CFPB require Aargon Agency, Inc to : Immediately delete this medical collection account from all consumer reporting agencies Cease any further reporting or disclosure of my medical information Provide written confirmation that this account has been permanently removed If this matter is not resolved promptly, I reserve all rights to pursue further complaints with the Office for Civil Rights ( OCR ) for HIPAA violations and any additional legal remedies available to me. | C20: Credit reporting | D20: Both collection and reporting language appear, but the requested remedy is deletion of an inaccurately reported collection tradeline; Credit reporting.
A21: 8125 | B21: The company currently servicing our mortgage reached out in XX/XX/XXXX to refinance our mortgage due to the low rates, so we agreed. We locked in a rate of 3.125 % on XX/XX/XXXX with NewRez and supplied them with all the upfront requested documentation and eSigned all necessary forms. It is now XX/XX/XXXX and we still have NOT closed on the refinanced loan and they are asking for more documents, and my husband to correct the figures multiple times on the documents provided by NewRez for the refinance ( incorrect escrow figure, property taxes, etc. ). We constantly reached out to the company throughout the multitude of months since starting the process in XXXX and were told various stories about how the loan would be underwriting soon once one more bit of information was verified -- and the information to be verified never was accurate to begin with for our loan. Or, there would be no response and no escalation even after we demanded status updates with set deadline dates for such information. We have lost out on four months of saving {$300.00} a month that the refinance should have secured had it closed at the end of XX/XX/XXXX as it should have closed, and we now can not refinance with an alternate company at the same rate as rates have now increased, and also, the loan office does not get paid until this loan closes so there are multiple parties effected by this company 's gross incompetence. | C21: Mortgage
A22: 8128 | B22: Kia Motor Finance has a deferment program which I applied for and instead of them trying to help me they refuse to - my loan will be 60 days late by the XXXX of this month and they will not help - they say they will approve you and then tell you that there is a document that you need to sign and send back however in the meantime they do not sent the document and this will impact my credit - they are not being helpful at all. | C22: Consumer loan | D22: The product is an auto loan from Kia Motor Finance; Consumer loan applies.
A23: 8129 | B23: Have filed multiple different disputes with Equifax for an account on my credit with XXXX XXXX XXXX that was opened under fraud. Each time there is no resolution, the account continues to show up on my report causing me to lose time by filing disputes and delay any credit related purchases that I may have. XXXX and XXXX have both already removed the account without delay. Complaints have already been filed with the FTC and Equifax still will not take action. | C23: Credit reporting
A24: 8130 | B24: I am stressed out because this company is violating my rights Under 15 U.S.C. 1681s-2 ( a ), data furnishers are required to report only accurate and complete information.Reporting unverifiable or inaccurate data is a violation of federal law. | C24: Credit reporting
A25: 8136 | B25: I did apply for the card but never finalized that I wanted because it was only for {$300.00} and they take {$80.00} of that for fees etc so I didn't want it and never confirmed that I wanted the credit card ... I don't even have the card in my possession... | C25: Credit card
A26: 8142 | B26: I attempted to withdraw money from my account to another bank account in my name. Marcus froze the funds and claimed that they needed onerous documentation from me ( a statement from my other bank sent to them via mail ) in order to complete the transfer. They also could not manually reverse the transfer, leaving my $ XXXX in limbo while Marcus decides what to do with the funds at their sole discretion. | C26: Money transfer or service
A27: 8166 | B27: I sold an item and shipped it via USPS Media Mail to a buyer named XXXX XXXX. She filed a PayPal dispute claiming she never received the package. This was false. She refused delivery and had the package returned to sender. I have the returned package in hand with a USPS label clearly marked " Return Postage Due = {$5.00} '' dated XX/XX/year> and stamped " Refused. '' Despite my evidence, PayPal ruled in her favor. The fraudulent dispute resulted in a {$19.00} reversal against me, plus I was charged {$5.00} in return postage caused directly by her refusal. Total loss : {$24.00}. I am requesting PayPal reopen and reverse this decision. | C27: Money transfer or service
A28: 8168 | B28: The credit bureaus must obey many laws, including the Fair Credit Reporting Act ( FCRA ). And according to the FCRA insert condition such as an incorrect balance an incorrect account number an undated late pay a missing field of missing field here such as status the wrong account type an incorrect a late pay after account was closed an inaccurate date of last activity an inaccurate date of last update a charge off listed as open a collection account with an inaccurate reporting dateLEAD BANK self XXXX POTENTIALLY NEGATIVE MONTHS Credit usage 0 % account Balance updated XXXX XXXX, XXXX Credit limit {$1000.00} Account info Account number XXXX Open/closed Closed Date opened XX/XX/XXXX Account type Revolving PAID CHARGE OFF VARIABLE RATE. PAID CHARGE OFF VARIABLE RATE. XXXX # XXXX Open/closed Closed Date opened XX/XX/XXXX Account type, Account, XXXX, XXXX Installment reported late payment XX/XX/XXXX XXXX XXXX XXXX XXXX PAYMENT Balance {$0.00} Balance updated XX/XX/XXXX, | C28: Credit reporting
A29: 8174 | B29: Our mortgage company 's loss/draft department are solely to blame for our issue. Not the insurance company or the VA. We had a catastrophic loss of our home and we have cooperated with everything they have asked, but they do not give us the funds we need and have paid out of pocket and taken from our retirement savings, at a heavy tax levied against us, and our personal savings. We had difficulty getting a contractor to over see the work. Our last contractor did nothing for 8 months. Nothing. So we became our own general contractor and got our permits and hired the sub contractors. I am attaching some of the emails we have written. So far we have asked for reimbursement from two contractors for the final completion of the exterior of the house and the excavation company that worked to remove the old burned house and dig/fill utility trenches, and prepare the ground for radon barrier and concrete pour. They did reimburse at least once for our underground plumbing work and the builder completing the outer shell of the house. We have been waiting for 4 weeks for them to pay the final bill to that company. | C29: Mortgage
A30: 8180 | B30: Subject : Repeated Account Closures After Approval Request for Explanation I am submitting this complaint regarding a pattern of behavior by Capital One that I believe may constitute an unfair or deceptive practice. Capital One has repeatedly approved my applications for credit cards, only to close the accounts shortly afterward citing a vague business decision without providing any meaningful explanation. This has occurred multiple times. Despite these closures, Capital One continues to solicit and approve new credit card applications for me. This creates a confusing and frustrating situation where I am led to believe I am eligible for their products, only to have the accounts closed again shortly after opening. I have no negative payment history with Capital One and have complied with all account terms. Because these approvals are being granted and then reversed repeatedly, I am concerned that this process may result in unnecessary hard inquiries on my credit report and, in some cases, the collection of annual fees before the account is closed. At this point, I am requesting that Capital One provide a clear explanation addressing the following : 1. Why my accounts continue to be approved and then closed shortly thereafter. 2. Whether I am internally flagged or otherwise deemed ineligible for Capital One credit products. 3. Why I continue to receive solicitations and approvals if the bank has no intention of maintaining a credit relationship with me. If Capital One has determined that I am not eligible for their products, I respectfully request that they cease marketing and approving applications for credit cards in my name. I am simply seeking transparency and fair treatment in this matter. Thank you for your attention to this issue. | C30: Credit card
A31: 8184 | B31: I have a a few loans with RISE. Last month when I looked at my credit report I had XXXX inquiry from this company now I have XXXX and they all are dated for different months in the same year. I understand that the company will pull my credit to approve the loan, but they can not place the inquires on the file 10mos after the loan has been paid off. | C31: Credit reporting | D31: Loan type is not named, but the complaint is about credit-report inquiries; reporting is the subject under the Protocol.
A32: 8203 | B32: I am filing a complaint against Cash app ( Block, Inc. ) due to inadequate customer service and unfair practices, which violate the Consumer Financial Protection Act ( CFPA ). Specifically, Cash App failed to take timely and effective measures to prevent and address fraud on their platform, leaving my account vulnerable and unprotected. Furthermore, their dispute resolution process was unfair and deceptive, as they did not comply with error resolution requirements under the Electronic Fund Transfer Act ( EFTA ) and Regulation E. These actions have caused significant inconvenience and financial loss, and I seek appropriate redress for these violations. | C32: Money transfer or service
A33: 8206 | B33: In XX/XX/2021, our mortgage payment was {$1500.00} instead of the normal {$1100.00}. I paid it and thought it was the difference for insurance. XXXX came around and it was high again. After tons of call and inquiring, they filed my property tax incorrectly. I got the necessary paperwork to them. They told us to use the 15 day grace period to allow them to correct the numbers and pay our mortgage. They say we will owe {$1500.00} this month. We should get a lower payment plus last months overpayment reimbursement. Ive called 29 times. Ive been told to shut up, Ive been hung up on 5 times. I get told different things every time. No one knows what to do or how to help. They just say pay the {$1500.00} and they will fix it. I need to know what happened to the {$600.00} escrow check they sent out, when it will be fixed, and to be certain it wont reflect on my credit score. Most unprofessional company Ive ever experienced. | C33: Mortgage
A34: 8207 | B34: Money was XXXX or XXXX from XXXX XX/XX/XXXXXXXX where I received my Direct Deposit Payroll, to XXXX XXXX XXXX XXXX XX/XX/XXXX The intent was to buy some shares of XXXX, since they are a Stock/Trading company. My deposit is not there. They can't find it. Initially I was given an availability date of XX/XX/XXXX then 2 days later it was changed to XX/XX/XXXX, which I clutched my pearls, and thought that was kinda a long time to hold one 's funds! : ( Why did the dates change twice, & now my funds are " stuck '' somewhere, waiting to be processed!? Chime says the didn't receive the REJECTED funds back yet that XXXX admitted to rejecting. I talked to a Gentleman named XXXX at XXXX who explained this unfortunate latest update to me! | C34: Money transfer or service
A35: 8213 | B35: I have a loan with United Wholesale Mortgage. I have not been able to reach ANYONE from customer service I had an insurance rep call me with the same problem trying to reach them They do not answer the phone and do not acknowledge even having my loan, and however long i try or whatever phone number i try reaching customer service on it just does not go through. | C35: Mortgage
A36: 8215 | B36: I have submitted multiple disputes regarding these accounts that is reporting inaccurately on my credit report. I have also submitted multiple reports regarding the account that needs to be updated These companies have refused to do work on disputes even though they're required by the law to do so. Account Name : XXXX | C36: Credit reporting | D36: No card is named; the complaint is explicitly about inaccurate reporting and disputes on the credit report.
A37: 8222 | B37: I received an email that my account was closed at XXXXXXXX XXXX XXXX on XX/XX/year>, with no stated reason. Since this email, my account is restricted and I am unable to access {$3300.00} in my account. | C37: Bank account or service | D37: Account type is not specified; closest fit is Bank account or service because the complaint is account restriction and inability to access the balance.
A38: 8225 | B38: XXXX & Equifax are reporting an erroneous collection on my credit report for XXXX XXXX XXXX - XXXX - I never received one notice regarding this debt, it just showed up on my credit report. This was paid | C38: Credit reporting
A39: 8244 | B39: According to 15 use 1681eb Everything must be 100 percent max accurate The credit bureaus keep disrespecting the laws. I showed them multiple times of how they are violating the Fair Credit Reporting Act. According to 15 use 1681 ( 5 ) The credit bureaus said everything was complete and accurate and I asked them how if the open date is wrong. Then I ask them to provide me description of the investigation according to 15 USC 1681 ( 7 ) and they never did. I have proof of my letter for that. Also according to 15 USC 1681 s-2 A person shall not furnish any information relating to a consumer to any consumer reporting agency if the person knows or has reasonable cause to believe that the information is inaccurate. This is violation after violation after violation. This is causing me stress because I have no hope with this system | C39: Credit reporting
A40: 8245 | B40: I am writing to formally contest the inclusion of fraudulent account in my Experian credit report. Despite submitting a dispute letters and the required documentation to the Federal Trade Commission ( FTC ), as per your guidelines, this account persist on my Experian report. After uncovering this fraudulent account, I contacted the relevant bank, which acknowledged its fraudulent nature and assured me of its removal from their records. Subsequently, XXXX and XXXX have both expunged this account from their records after verifying its fraudulent status. I am puzzled as to why Experian continues to report this fraudulent account, especially since the other credit bureaus have already removed it. I have completed all necessary steps and furnished all relevant documentation to substantiate my claim of identity theft. I hereby request a comprehensive investigation into this matter and the immediate removal of this fraudulent accounts from my Experian credit report. The bank has confirmed the fraudulent nature of this account, and its persistence on my credit report is unjustified and detrimental to my creditworthiness. XXXX XXXX XXXX XXXX XXXX XXXX XXXX XXXX XXXX XXXX XXXX | C40: Credit reporting
A41: 8248 | B41: I used Moneygram on XX/XX/XXXX to send XXXX usd. And i git a messsage saying the money was sent with the reference number XXXX, but minutes after i got an email saying the opened a case XXXX. They lied because they said it was the receivers bank problem and i told them many times that we spoke with the branch manager ( XXXX bank ) and they are very opened to receive the money so we drove many times to the branch wasting money and time. Please we need our money back because we have so many things to pay for. XXXX XXXX XXXX XXXX | C41: Money transfer or service
A42: 8250 | B42: Request for Update to Paid As Agreed Never Late ( PAANL ) Violation of 15 USC 1637b To Whom It May Concern : I am writing to formally request an update to my credit report regarding my account with : 1 ) XXXX XXXX XXXX XXXX XXXX to the provisions of the Truth in Lending Act, specifically 15 USC 1637b, a creditor may not treat a payment on a credit card account under an open-end consumer credit plan as late for any purpose unless the creditor has provided the required notice, as outlined in section 1637b. Section 1637b of the Truth in Lending Act clearly states that a creditor must inform the consumer in writing, within a reasonable period, if a payment has not been made within the grace period. Specifically, if a payment is considered late, it must not be treated as such unless the creditor notifies the consumer at least 21 days prior to the due date. As of today, I have not received any such notice regarding the account referenced above, nor have I been notified of any payment being considered late. In light of this, I am requesting that my account be updated to reflect the accurate status of " Paid As Agreed Never Late '' ( PAANL ) as no late payments were reported or properly documented. Since no notification of a late payment has been issued in compliance with the law, my account status should accurately reflect that it was paid on time and as agreed. I request that you update my credit report accordingly and remove any negative reporting related to this account. I expect a response within 30 days, as required by the Fair Credit Reporting Act ( FCRA ), and would appreciate your prompt attention to this matter. If you need any additional information or documentation to process my request, please do not hesitate to contact me. I appreciate your cooperation in ensuring that my credit report is accurate and complies with all applicable laws. Sincerely, XXXX XXXX | C42: Credit reporting
A43: 8251 | B43: XX/XX/XXXX Subject : Dispute of Inaccurate Late Payment Reporting on Account # XXXX Dear CFPB, I am writing to formally dispute inaccurate information being reported on my credit file regarding the XXXX account ( # XXXX ). According to the Fair Credit Reporting Act ( FCRA ), you are required to ensure the accuracy of the information reported and to investigate disputes promptly. Upon reviewing my credit report, I found that the payment status for this account continues to indicate " 30 days late, '' which is inaccurate. I have consistently made on-time payments for this account, and I have attached relevant documentation to support this claim. Here are the details of the account : High Balance : {$2000.00} Date of Last Activity : XX/XX/XXXX Date Reported : XX/XX/XXXX Date Opened : XX/XX/XXXX Balance Owed : {$0.00} Closed Date : Not Available Account Rating : Paid Account Status : Closed Payment Status : Late 30 Days Creditor Remarks : Consumer disputes- reinvestigation in progress ; Closed or paid account/zero balance Two-Year Payment History : Indicates " OK '' for all months but continues to show a " 30 Days Late '' status inaccurately. I request that Equifax provide a detailed description of the investigation procedure conducted to verify this account 's payment history, as required under 15 USC 1681i ( a ) ( 7 ). Furthermore, I request documented evidence supporting the late payment claim, including specific dates, amounts, and correspondence that validate this reporting. In the absence of valid evidence, I demand that the payment status for this account be updated to " Paid As Agreed Never Late '' immediately. Failure to comply with this request within the 30-day timeframe outlined in the FCRA will constitute a violation of my rights as a consumer. Thank you for your prompt attention to this matter. I look forward to your response and resolution. Sincerely, XXXX XXXX XXXX XXXX | C43: Credit reporting
A44: 8257 | B44: Navy Exchange ( NEX ), the " XXXX '' onboard US XXXX bases, offers currency exchange for personnel stationed overseas ( in XXXX ) to pay their off-base rent. However, the exchange rate offered is always 2-3 % less than the Bank Rate for US dollar to XXXX XXXX exchange. To offset this, the Navy Exchange provides a {$10.00} gift card for use at the NEX, for each month paid. However, this is inequitable because the gift card is always for the same amount, regardless of the monthly rent amount ... so a single military member with an $ XXXX/month ( equivalent ) rent payment derives more proportional benefit from this {$10.00} gift card than a military family whose rent could be closer to $ XXXX ( equivalent ). | C44: Money transfer or service
A45: 8263 | B45: Debt Collector ( s ), Obligors, Debtors XXXX and XXXX XXXX are attempting to collect an alleged debt of the Consumer. The named debt collectors are engaged in illegal acts by simulating a judicial court affiliated with the United States. The debt collectors were served numerous notices under federal consumer statutes but fail to comply. The debt collectors are attempting to seize the private property, consumer goods of the Consumer under the guise of Foreclosure which is not being performed in a competent judicial district under 15 USC 1692i. The debt collectors are not exempt pursuant to XXXX, XXXX under federal law. This debt collector is taking illegal non judicial actions in violation of the FDCPA, 15 USC 1692, Identity Theft, XXXX. The FTC has a report by the consumer. | C45: Debt collection
A46: 8264 | B46: Hello, I got asked to create a song. They offered to pay me XXXX but sent XXXX on " Accident ''. I deposited the check into my wellsfargo account the XXXX of XX/XX/2021. The check cleared and was in my account, so I sent them 4 payments of XXXX, only to have that check bounce 3 days later. I wouldnt sent them any money if the check wouldn't of cleared. I didn't get any notifications that it could be a fake check. I didn't have any pendings over the check it was all in my account. The account the contacted me was through XXXX, this is the account. XXXX The email address the check came from is XXXX Hope this information helps! | C46: Money transfer or service
A47: 8270 | B47: I had a credit card account with chase bank the was closed due to payment issue. But i paid down full amount on the time. My credit score is outstanding im trying to apply for a credit card with chase and its denying. | C47: Credit card
A48: 8274 | B48: I am unemployed seeking employment and I have been denied employment because of the fake news contained in my credit file. There are numerous inquiries that I have never engendered and I've never even heard of these companies. There are fake telephone numbers on my credit file I have never had, there are fake address to places where I've never lived too. My credit file with Experian contains a lot of fake news. The information contained in the credit file belongs to the consumer and if it is inaccurate or contains misleading information, the consumer has the right to correct the information. While I was legally XXXX for XXXX, my identity was stolen from me and I took appropriate action notified the Credit Reporting Agency ( CRA ) in this complaint with a Fraud Affidavit and proof of legal incapacity. I notified federal law enforcement. The CRA in this complaint told me to contact all the companies. I did. I notified the companies that inquired on my credit file to remove and/or correct the erroneous information from my credit file. They all told me that the CRA does that, not them. I then wrote the CRA in this Complaint that I've already spoken to the various companies that inquired in my credit file and they all told me there's nothing they can do about it. I being jerked around by Experian. | C48: Credit reporting
A49: 8278 | B49: I am filing a complaint against Cash App ( Block , Inc. ) due to inadequate customer service and unfair practices which violate the Consumer Financial Protection Act. Cash App failed to take timely and effective mesures to prevent fraud on their platform, This has left my accounts and finances vulnerable and unprotected. Their dispute resolution process is deceptive and unfair as they did not comply with the error resolution requirements under the Electronic Fund Transfer Act and Regulation E. This has caused signifigant inconvenience and financial loss and I seek appropriate redress for these violations. | C49: Money transfer or service
... A54: 8299 | B54: Citizens One Bank is purposefully making it difficult to remove PMI. I submitted a request to start the process 3 weeks ago and have not received a call, email, or secure message from the company with ALL information for removing it. They have only sent a message saying they will send another message via snail-mail. They REFUSE to give me the contact information for the PMI department. | C54: Mortgage
A55: 8301 | B55: I am submitting this complaint regarding an issue with my credit report that is negatively affecting my financial standing. I have made multiple attempts to resolve this matter directly with the creditor/furnisher, but they have failed to provide an adequate response. Below are the details of my complaint : XXXX. Charged-Off Account or Collection Account Creditor/Collection Agency Name : SXXXX XXXX XXXX XXXX XXXX XXXX XXXX XXXX XXXX XXXX XXXX XXXX XXXX XXXX XXXX XXXX XXXX XXXX XXXX XXXX XXXX XXXX XXXX XXXX XXXX XXXXXXXX Issue : This account was charged off/placed in collections without proper notification or validation of the debt. I requested validation of the debt per my rights under the Fair Credit Reporting Act ( FCRA ) and Fair Debt Collection Practices Act ( FDCPA ), but the creditor/collection agency failed to provide sufficient documentation. The reported balance and payment history contain inaccuracies that I have disputed with the credit bureaus, yet the creditor refuses to correct or remove the erroneous data. The account was sold to a third-party collector, yet it remains listed under the original creditor, creating duplicate reporting and unfair harm to my credit profile. I am requesting the immediate deletion of this inaccurate and unverifiable account from my credit report or proper documentation proving its validity. | C55: Credit reporting | D55: Both collection and reporting language appear, but the requested remedy is correction/deletion of inaccurate credit reporting; Credit reporting.
A56: 8307 | B56: In XXXX of XXXX, property taxes were waived in the city of XXXX due to 100 % service connected XXXX. Penny Mac issued a refund in XXXX of XXXX for money paid to escrow for property taxes for the year. I. XX/XX/XXXX, the escrow paid the property taxes to the city of XXXX in error in the amount of XXXX. Since the end of XXXX I have called over 10 times between the lender and the city of XXXX to obtain the refund. I continually have to wait 14 business for a response that doesnt come. As of today XX/XX/XXXX. Penny mac has a cashed check with a check number for the property taxes refund and refuses to refund me even though we closed our loan out with them in the beginning of XXXX. | C56: Mortgage
A57: 8309 | B57: THIS IS NOT A DUPLICATE! same problem, same company, different co-signer. I have been asking Navient to release my cosigners for 8 months now and can not get any specifics on why they are refusing to do so. I sent a letter to Navient, which they received on XX/XX/XXXX, requesting an explanation, in detail, for why they refuse to release cosigners even though we met their stated requirements. As of today, XX/XX/XXXX, they still have not answered me. Plus they keep sending ridiculous answers for why they can not answer my questions. Playing games to drag it out longer so they get what they want. terrible, terrible, terrible, crooked, lying, stealing company. Some things they tell you only over the phone, some things they only tell you snail mail, some things they only tell you by fax, it's absolutely criminal. | C57: Consumer loan
A58: 8310 | B58: On XX/XX/XXXXXXXX while vacation in XXXX, MO we attended an owners ' meeting and a man named XXXX XXXX sold us ownership in XXXX XXXX XXXX for {$3900.00}. This company was supposed to rent out any unused XXXX XXXX points and pay us for them. After receiving our XXXX XXXX points in XXXX, I contacted or attempted to contact XXXX XXXX to find out how to proceed. I called the numbers provided on XXXX XXXXXXXX XXXX business card but the numbers are no longer in service ( XXXX and XXXX ). I also emailed XXXX and that address does not exist. I contacted the executive offices of XXXX in XXXX where we supposedly purchased ownership with XXXX XXXX and they informed us that XXXX XXXX had been fired. I had no way to get in touch with this group and I contacted the credit card company to which the {$3900.00} was charged and informed them that this was a fraudulent charge and that we were unable to contact anyone ( even the info provided on the charging line of the credit card statement ( XXXX ) and that we had not received any services from them for which we had paid. The card is a Barclays XXXX XXXX card. Barlays immediately issued a provisional credit for the {$3900.00}. On XX/XX/XXXX I received a letter from Barlays indicatingthat indicated that they had received a response to validate the transaction and that the merchant had not violated the terms and condidtions of the sales agreement and that the {$3900.00} would be reapplied to our account. Again this morning XX/XX/XXXX I attempted to contact XXXX XXXX using the email address provided on the contract and received a reply that the address does not exist ( XXXX ) and I called the phone number provided ( XXXX ) and the number has been disconnected. I am going to provide this additional information to Barclays and continue to protest the charge because evidently either this company does not exist or has gone out of business because WE HAVE NOT RECIEVED ANY SERVICES that this contract provides. | C58: Credit card
A59: 8323 | B59: Yard card finances lawn equipment through td bank. I mail my payment through my online account at XXXX XXXX every month. They applied my XXXX payment to the wrong account. I have contacted them by phone and email and they can not straighten out the problem. My account number with yard card is XXXX. The account they credited payment to was XXXX. | C59: Consumer loan
A60: 8326 | B60: After receiving a copy of my 3 bureau credit report in XX/XX/XXXX, I noticed that Pro Collect was reporting a balance of {$1000.00}. I am unfamiliar with this company so I reached out to them in hopes to get some clarity on this alleged amount due. During the call I was told that they are a third part and have been collecting on the account since XX/XX/XXXX. I requested, both in writing and verbally, a copy of the contract and /or validation of this account on XX/XX/XXXX and have yet to receive either. The presence of this account has made it difficult for me to obtain even the smallest amount of credit and has caused a great strain on my lifestyle. I also disputed this account directly with the 3 CB 's and they came back verified. I requested the name and documents used to verify this account well over 30 days ago. According to the FCRA it must be deleted from all reporting entities. I am requesting that Pro Collect comply with FCRA, 15 U.S.C under Section 611 ( a ) ( 5 ) ( A ) ( i ) and delete this account immediately. | C60: Credit reporting
A61: 8333 | B61: I have been dealing with only Wells Fargo and now as of XX/XX/2021, they are saying that being the servicer of the loan they can do anything, right or wrong and not be responsible. So now I am bringing XXXX XXXX XXXX in and let them see what their Servicer have been doing. | C61: Consumer loan | D61: Loan type is not named; using Consumer loan as the standing generic-loan tie-break. The complaint is not specifically about a mortgage.
A62: 8335 | B62: Mostly all of XXXX Ive been getting random charges of purchases clearly I wasnt making being in my hometown and the charges coming out from different states. XXXX XXXX XX/XX/XXXX there have been multiple withdrawals and purchase attempts with some actually going thru because I didnt have my card locked. XXXX of XXXX someone transferred a large amount of my funds to an unfamiliar person for well over {$600.00}! From XXXX to current I continue to get random charges of attempts with some being successful to merchants like XXXX. All of these problems came with me calling the hotline number online only to be told We will look into it and get back and never recieved any call or feedback. | C62: Money transfer or service
A63: 8337 | B63: I made a one time purchase at Macys and the sales person offered me this card. I explained that I did not want the card, because I would use it only at that particular moment and not anymore. I do not live in the US. The sales person guarantee that there would be no charges involved in making that application so I could use the card one time. There were no fees. I used my son 's address and told her. I was surprised with this letter from the debit collector. I reserve my rights to use a lawyer again the company if I have any further inconveniences for this matter. I hope the matter gets solved and wait for an answer. | C63: Debt collection
A64: 8339 | B64: A loan under my name was takin out in XXXX XXXX XXXX I have filed a complaint against LVNV Funding LLC. before, and I have not gotten any help. I just sent them another message today, and asked to speak with a manger or higher up. I also wrote them a message in the past asking to talk to a manger or higher up. That never happened. My credit score continues to decrease because of this fraudulent loan, and LVNV Funding LLC does not help resolve the matter. I do not want my score to decrease again. I have also contacted other law enforcement agencies regarding this, and hope they can help me. | C64: Consumer loan | D64: The complaint concerns a fraudulent loan taken out in the consumer's name; the credit-score impact is secondary, so Consumer loan applies.
A65: 8342 | B65: On XX/XX/year>, I noticed multiple unauthorized XXXX XXXX charges on my Chime debit card ending XXXX, totaling approximately {$290.00}. I immediately turned off my card, reported the transactions, and had a replacement card issued. At the time these transactions occurred, my original card was turned off in the Chime app, meaning it should not have been able to process any debits. I submitted my official XXXX XXXX purchase history, which clearly shows no matching transactions, proving that the charges were not made on my XXXX account or any of my devices. I filed my formal dispute on XX/XX/year>, after the transactions finished pending. Chime closed the dispute in less than XXXX hours over a weekend without conducting a reasonable investigation or providing any verification data. The only proof Chime supplied was a list of transaction entries, with no device logs, IP data, or merchant authorization details connecting me to the purchases. Under Regulation XXXX ( XXXX CFR XXXX ), financial institutions must perform a reasonable investigation before denying a consumers claim. Chime and its partner bank, XXXX XXXX XXXX, XXXX, failed to meet that requirement. | C65: Money transfer or service
A66: 8345 | B66: Coinbase locked my account on XXXX to " verify my identity ''. I've had the account for many years and my portfolio is in excess of $ XXXX. I have done everything they asked to restore access to my account but they require proof of where I obtained my capital from. I do not have such documents. My seed money came from a wrongful death suit and I explained that. Ive paid my taxes every year, they have my ID and my SSN, I've sent documents of every transfer I ever made from my bank account to Coinbase. They have given me a few days to submit these documents but refuse to tell me what will happen if I can not. I have asked them, they have dodged every question and refused to even tell me what documents will satisfy them. I can not make trades or withdraw any of my money. | C66: Money transfer or service | D66: Crypto-platform account access is outside the seven named scopes; Money transfer or service is the closest fit.
A67: 8356 | B67: I was approved for a XXXX XXXX loan modification and had payments due in XX/XX/XXXX., XX/XX/XXXX, and XX/XX/2018. When I called to make the first payment on XX/XX/XXXX ( I had until the last day of the month ) they informed me my house had been sold in foreclosure to XXXX XXXX. I have been battling this with both Loan Depot and with XXXX XXXX ever since XX/XX/XXXX. and have been told numerous times that it was Loan Depot 's fault for not advising the foreclosure dept. They passed me off to different agents this entire time where I would have to explain the situation all over again. They sent out company wide emails while I was one the phone explaining that it was a wrongful foreclosure but nothing has come of it. XX/XX/XXXX XXXX XXXX sold my house to a renovation company and I have just received my 10 day notice to vacate. I've learned this is called Double-tracking and it is illegal. I can not find any attorney to help me for some reason. I will fight this till they kick me out of my home but this is my daughter 's home. She was born here. She is XXXX years old. I had $ XXXX in equity in the home but lost my business and had trouble making payments. I though this Flex Mod. was my saving grace and it ended up being the hardest thing I've ever dealt with in my life. Whoever reads this, I need help please | C67: Mortgage
A68: 8359 | B68: I am a borrower impacted by the Joint Consolidation Separation Loan Act I contacted Mohela about our loan # XXXX by phone the beginning of XXXX asking for a 30 day forbearance and they verbally granted it. But they are still sending a bill for it. I emailed them on XX/XX/XXXX, XX/XX/XXXX, XX/XX/XXXX, XX/XX/XXXX, XX/XX/XXXX explaining this to them and they only responded with an explanation that I already have a forbearance on this loan, but they are referring to my other loan # XXXX which is part of the pandemic forbearance. I tried calling and was placed on hold for 120 minutes and when someone answered, they took my personal information and put me on hold back at the beginning cue that said " your approximate hold time is 100 minutes. I had to go back to work and could not hold for an additional 2 hours. I also completed my annual recertification information on XXXX and they are sending me letters stating that I have not done it and increased my payment by {$300.00}. I also emailed asking for a PSLF forbearance due to our application sent in for the temporary waiver and they have not granted it. | C68: Consumer loan | D68: The complaint is about a Mohela student loan and its forbearance/recertification servicing; Consumer loan applies.
A69: 8365 | B69: BB & T failed to notify me of an increase in my monthly mortgage payment. I continued to make monthly mortgage payments and BB & T continued to receive and accept my on time payments. In XXXX and XXXX BB & T reported my mortgage payments as not as being paid for two months to the credit rating agencies. I learned of this when I called BB & T to inquire as to why I had not received a new mortgage coupon payment book. I than wrote BB & T and informed them I never received any notification from them regarding the change in mortgage rates and its effect on my monthly mortgage payment. I requested BB & T provide proof of a delivery confirmation of mail sent to me and that it was successfully delivered. Any financial matter that could have an adverse effect on anyone 's credit rating should require a delivery confirmation. I have paid my monthly mortgage payment on time every month and BB & T has received payment before the due date. The months in questions are XXXX and XXXX 2016 which XXXX shows funds posted, received and accepted by BB & T. When spoke with a BB & T representative I was informed that the payments were posted to my account. How can funds received for on time payment by BB & T get posted and reported as late - where did my money go and why is BB & T allowed to conduct such a questionable banking practice? | C69: Credit reporting
A70: 8366 | B70: I applied for Chase freedom Unlimited credit card and was denied. Upon denial I contacted Chase, I spoke with a representative that told me I was denied because of my credit score and more information would be sent by mail. I received a notice by mail stating the same thing, that I was being denied due my credit score. I then sent Chase an adverse action letter and a notice of default/ opportunity to cure and they have now defaulted. The silence from Chase is XXXX. | C70: Credit card
A71: 8369 | B71: XXXX XXXX restricted my cards because someone paid the balance off on both of my credit cards without my knowledge of who it was they wanted me to submit a bank statement to prove it was not me but the card that paid the bill off in full was not mines I do not have an account with that bank after not being able to submit that statement they returned the balances back to my credit cards and close my account my accounts were in good standing at my venture card was {$2800.00} and my quick silver was {$2500.00} is what was paid off and than returned back to the original balances I tired to explain to the fraud department but nothing happen I called them everyday for XXXX weeks and they were still asking for a statement from me and I kept telling them I do not have a statement that is not my account they also tried to charge cell phones at XXXX but the card was declined this all happen in XX/XX/year> and they paid my cell phone bill for {$100.00} | C71: Credit card
A72: 8372 | B72: This is a follow-up to my existing complaint ( ID XXXX ). On XX/XX/year>, I met with XXXX XXXX ( XXXX XXXX XXXX at XXXX XXXX. XXXX XXXX XXXX ). She stated she is unable to provide any written or verbal explanation for the closure of my account, claiming the decision was not hers and she was not given any details. She confirmed the decision originated from someone above her level. On XX/XX/year>, I sent a formal demand to Old Nationals Legal Department requesting they immediately reopen and support my remaining ~ {$11000.00} in XXXX XXXX disputes. I have received no substantive response. The closure of my account while these disputes were still open has made it impossible to resolve them. I am requesting CFPB assistance in forcing Old National Bank to reopen and fully support my remaining XXXX disputes and provide a written explanation for the account closure. | C72: Bank account or service
A73: 8379 | B73: I disputed an item due to cancelling and never receiving merchandise, Wells fargo took the word of the merchant that I did n't cancel so they reversed the credit. I felt this was unfair having being charged XXXX for something that I never received and was told would be cancelled and no further shipments. Wells Fargo wont reopen its investigation and says I did n't cancel, why would I lie? this is a large bank just bullying the little guy | C73: Credit card | D73: The narrative does not explicitly identify a card, but the Wells Fargo merchant-charge dispute is most consistent with the Credit card scope.
A74: 8382 | B74: Validation of Debt Request - SPRINGOAKCAPXXXXXXXX XXXX XXXXXXXX XXXX XXXX XXXX XXXX XXXX XXXX XXXX I am disputing this account as inaccurate and request full validation, including the original signed agreement and complete payment history. If you can not verify this debt, you must delete it from all credit reporting agencies. Pursuant to the Fair Debt Collection Practices Act ( FDCPA ) 1006.34, I am entitled to receive verification of the debt you claim I owe. I dispute the validity of this debt and, as such, I am exercising my rights under the FDCPA to seek verification. Please provide the following information within the next 30 days : 1. The amount of the debt claimed. 2. The name of the original creditor. 3. A copy of the agreement, contract, or other instrument that created the debt. 4. Verification that you are licensed to collect debts in | C74: Debt collection
A75: 8383 | B75: XXXX servicer granted us a forbearance because of our toddlers large medical needs and recent XXXX which also happened to be during covid 19 ( my husband was out of work as well ) and said they would put the amount to the back of the loan. Over the past week, they have been trying to demand the forbearance in full because they say the loan carrier inspire home loans said its either we pay full or nothing. I have supporting documentation that states we can resume our regular payment on XX/XX/2023. They accepted a payment in XXXX {$1400.00}. Over the month, we have been trying to set up a REPAYMENT plan now that our forbearance has ended. Since they will not place it on the back of the loan like they initially told us they would. We can pay our standard {$1500.00} a month plus an extra {$1000.00} a month for a total of {$2500.00} for 12 months. And have seen no results.. inspire home loans said they need to speak to their legal team about repayment plans, ( they are trying to say {$4000.00} if they get the ok from their legal team a month even thought we only owe XXXX in forbearance and it should be able to repay over a 12 month span ) and they cant risk putting the forbearance to the back of the loan even though our house is worth double the amount owed. Inspire home loans even had the nerve to transfer us to the foreclosure department, where they told us we werent in foreclosure.. & then a servicing manager asked for the forbearance documentation that I have because she couldnt access it herself because she said loan care was hanging up on her.. its been an absolute nightmare. I even offered to pay them {$4000.00} on XX/XX/XXXX. They would not take it. | C75: Mortgage
A76: 8384 | B76: Dear NAVY FEDERAL CR UNION ], This letter serves as confirmation that the debt associated with my then account has been paid in full as of [ XX/XX/year> ]. No further balance remains on this account, and it is now considered closed. We appreciate your prompt attention to this matter. If applicable, we will notify the relevant credit reporting agencies to reflect the updated status. Please retain this letter for your records. Should you have any questions, feel free to contact me. | C76: Credit reporting | D76: Product is not specified; selected Credit reporting because the requested action is to reflect the paid-in-full status with credit reporting agencies.
A77: 8389 | B77: My identity was compromise since XXXX I was out of the country for five years upon my return. I find out all my identity was compromised. Multiple account was opened under my name on my credit report. I reported this matter to the law-enforcement agency I received the report from the police department. I also submit a complaint to XXXX FBI I was advised by the quality report advisor from XXXX to generate and submit my report through FTC. Your time is highly appreciated. Please help me with my concern. My credit is all I have. Thank you for your time. | C77: Credit reporting
A78: 8390 | B78: They claim I activated an XXXX Rate Sale offer with a promotional rate through XX/XX/22. I did not do this. I would like to see proof and the details of this offer. It has affected how they processed my payments on balance transfers. | C78: Credit card | D78: No card is named, but the promotional rate and balance-transfer payment handling point to a credit-card product.
A79: 8392 | B79: I attempted to purchase XXXX XXXX tickets through PayPal using the Pay Later / XXXX financing option. When I completed the purchase, the PayPal screen clearly showed the transaction as DECLINED. Because it was declined, I reasonably assumed the purchase had failed. Instead of honoring the financing plan I selected, PayPal attempted to force the charge through by splitting the purchase into XXXX separate charges of approximately {$1200.00} each, all processed at the same moment. I never authorized XXXX separate charges. I authorized only XXXX financed transaction under the promotional XXXX plan. I did not receive any confirmation email, receipt, itinerary, or e-ticket from PayPal or XXXX XXXX. The airline later informed me that they sent the ticket information to an old and inactive email address unrelated to the email used for the PayPal transaction. Because the payment appeared as declined, I had no reason to expect any ticket or further action. Days later, my debit card was unexpectedly declined. When I checked my bank account, it was overdrawn by nearly {$5000.00} because PayPal had attempted to process the XXXX unauthorized charges. When I tried to dispute the issue in the PayPal app, the system would not allow me to file a claim until the charges cleared. After they cleared, I submitted the dispute, but PayPal denied all XXXX claims individually. PayPal is now attempting to collect almost {$5000.00} for charges I never authorized and for a service I never received. I am requesting CFPB assistance because PayPal failed to apply the financing option, processed multiple unauthorized transactions, caused a significant overdraft, denied my disputes, and is now threatening to send this to collections. | C79: Consumer loan | D79: PayPal Pay Later/financing is the substantive product; the payment/charge mechanics are incidental, so Consumer loan applies.
A80: 8414 | B80: Pressler and Pressler in New Jersey has been pursuing me for a medical debt of roughly {$1200.00} for the past several months. I initially set up a payment plan as I receive low income and am supporting my 14 month old daughter. I set up this payment plan in response to being sued by Pressler and Pressler with no warning. After several months of being invoiced and paying them I stopped receiving invoices. With absolutely no warning I discovered that Pressler and Pressler had garnished and frozen my bank account in attempt to collect the debt. I called them to try to resolve the issue and the only thing they would allow me to do was make a payment on a payment plan, however they would not release my bank account to me, claiming that I needed to hire a lawyer to proceed. I had to pay them using a credit card, which I am not worried I can not pay because my bank account remains frozen. The gentleman I spoke to told me that if I do not make payments I will be held in contempt of court and will possibly face charges or legal action. Without my bank account I am now unable to pay for my housing, my credit card bills, and most importantly, provide for my daughter. | C80: Debt collection
A81: 8418 | B81: I noticed that MRS BPO LLC reported a {$320.00} collection account on my XXXX credit report, listing XXXX as the original creditor. I do not owe this debt and have no record of having any account with XXXX. I contacted MRS BPO LLC to request validation of this debt, including proof of the original account, contract, and billing statements, but they did not provide any documentation to show that the debt is mine. Despite my request, the company continues to report this information to XXXX, which is negatively affecting my credit. I am requesting that the CFPB review this matter and require the company to either provide full verification of the debt or remove the inaccurate collection account from my credit report. | C81: Credit reporting
A82: 8420 | B82: On XX/XX/2023 I called XXXX XXXX to dispute information that was reporting incorrectly on my credit report. I was transferred to the Credit Reporting Department with XXXX XXXX and was told that " your account has been purged and is no longer in our system ''. I then asked if she could at least pull up my payment history on the account and she said, " No, I can't pull up anything about you in our system because your account has been purged from our system ''. On that same date, following the call with XXXX XXXX, I filed Credit Disputes with Transunion and XXXX online. I submitted a dispute letter and several files of evidence to support my claims. Transunion completed their investigation within XXXX business days and XXXX also completed theirs within XXXX business days. Neither of the Credit Agencies updated my credit reports with the disputed information although they both did make minor changes. If XXXX XXXX has told me themselves that my account was purged and removed from their system, how did Transunion and XXXX verify any of the information that is showing on my credit report or the disputed information? The credit agencies actually removed half of my payment history from the disputed account. I was showing 79 % of on time payments prior to the dispute and because much of the monthly payment history was removed, my on time payment history dropped to 52 %. This account has been closed for XXXX years and there haven't been any additional payments made on the account once it was closed. So, there's no way that my actual payment history percentage should have changed as that's not what the dispute was regarding. | C82: Credit reporting
A83: 8433 | B83: WESTLAKE FINANCIAL SERVICES is reporting on my personal credit file with ( XXXX ) credit reporting agency . This account was opened fraudulently. Ive informed all parties of the issue & provided the necessary documentation to support my claim. The credit reporting agency ( CRA ) & data furnisher ( DF ) are not complying with federal law in regards to identity theft. Additionally, the credit reporting agency & data furnisher have not provided me with any evidence of an open contract, signed contract or any valid proof this was opened, authorized or created by me. Since this is a strict violation of FCRA laws I need the account removed from my file. WESTLAKE FINANCIAL SERVI XXXX Opened XXXX XXXX, 2020 Balance {$8300.00} | C83: Credit reporting
A84: 8437 | B84: I had an account that was submitted to Midland Funding for collection. I logged into Midland Funding 's website to resolve the account. When I did this I noticed there was another account in the collections tab for XXXX XXXX with a balance of {$9000.00}. I opted to chat with a represenative and when I asked her how I dispute these charges and I didnt know the account she told me there was nothing she could do to help me. I checked my credit reports and the account isn't on them for me to dispute there so I logged back into Midland Funding and chatted with another represenative who was slightly more helpful. I explained to her that I needed to dispute the account and any/all charges associated with it. I told her that this account wasn't on my credit report and I asked for details on the account. I was told the account was opened in XXXX, closed in XXXX due to non payment and that it had been placed with their agency for collection. Now when I log back into Midland Funding the status is now " in legal collection ''. I asked repeatedly how to dispute this and finally she told me I could either file a police report ( from XXXX????? ) or file a complaint with the FTC which I wasn't aware I could do. So in summary here is an account from XXXX, I happened to resolve an account with Midland Funding and now they are persuing me for 1 ) an account I didnt open and have no knowledge of and 2 ) Interestingly enough NOW they decide to contact me for payment on this account once I've satisfied another. I think what happened was they saw that I resolved an account now they are trying to get me to pay ( from XXXX ) an account I'm asking help with disputing and they dont want to help me with it. This is fraud and all I was asking for was help, I suppose I shouldn't have expected any help from a company who plans on suing me for an account I didnt open. | C84: Debt collection | D84: No card is named; the complaint is explicitly about a collection agency pursuing an unknown account and putting it into legal collection.
A85: 8441 | B85: I have asked requested the following personal statement be placed in my credit report and related to all who request my report. THe statement meets the word and character requirements but the reporting agency will not place this on my report as requested. " My ID was stolen, in two security breaches. Found on the dark web, my XXXX & XXXX cards were used without authority. XXXX & XXXX were notified, provided copies of law enforcement reports obtained. I disputed the accuracy & completeness of XXXX & XXXX adverse reports to the three credit reporting agencies. Each agency gave XXXX & XXXX, notice as an adverse information furnisher. XXXX & XXXX failed to, conduct a reasonable investigation of each dispute ; review all relevant information ; modify, delete, or permanently block the reporting of XXXX & XXXX adverse information. '' | C85: Credit reporting
A86: 8444 | B86: on XX/XX/23 my phone was stolen at my neighborhood pool and the thief got into my account and transfer IRS check out of my account in the amount of XXXX. I sent in all necessary documents such as a police report and FBI report. The investigation team sent me documents of how the investigation came back as no error and it showed the IP of my phone that was stolen and the times of when the transfer happened i also had a XXXX XXXX XXXX XXXX and im seeing XXXX XXXX listed on the investigation doc & i now have a XXXX XXXX XXXX & also had an address that was 28 minutes from my home address that i have no knowledge of when the transfer happened. They also dont have the name of financial institution that initiated charge on the document. | C86: Money transfer or service
A87: 8449 | B87: I purchased an American Express Bluebird card at the local XXXX. I loaded it with {$500.00} cash. After reviewing the disclosure document enclosed with the temporary card, I requested a refund of my money. I never used, activied or signed the card. I called XXXX days after the purchase. I was told when I called to check status of refund, the refund was processed on the XXXX of XXXX. I requested the refund on the XXXX. Fine, it was processed late, but I waited, going to the post office and calling the XXXX day, when the check was not received. I was put on hold and left on hold not once but twice, lied to by he first clerk who actually told me they do not process refunds, which I replied that the disclosure states quite clearly that you DO. He then put me on hold, in the ruse to get a manager, and never came back. I have been going back and forth with this since, I still have not received my refund, and the delay caused me financial setback, and stress, XXXX, pain and lack of sleep. I am at my witts end with this I can not tell you how this has caused me so much XXXX and distrust. I can not comprehend what is going on and why. Please help me get me cash refunded and the financial loss I suffered as well. | C87: Bank account or service | D87: Bluebird is a prepaid stored-value card/service rather than a credit card; the seven-category set has no prepaid category, so Bank account or service is the closest fit.
A88: 8453 | B88: Navient ( formerly XXXX ) has been harassing me DAILY, calling my work/office phone numbers ( in-office and work mobile ), as well as sending me faxes at work and calling my personal mobile phone number throughout the day. They are jeopardizing my job with this incessant harassment. I have sent them a cease and desist letter, as well, and I have copies of this. | C88: Debt collection
A89: 8455 | B89: I reported my card to cash app as stolen, the cancelled my card never put a provisional credit on the account even after the police report was sent to them. They cancelled the card again and said they were closing the case. XX/XX/XXXX I lost a couple debit cards and credit cards. | C89: Money transfer or service
A90: 8461 | B90: Chase is discriminating against me and opened a brand new business credit card for me and then literally shut it down 1 week later. This is wrong. I have perfect credit. they approved this account, I did not even get a chance to use it and they closed it. I was a victim of fraud last year and Chase is discriminating against me and closed down all of my cards due to ME BEING A VICTIM > this is illegal. | C90: Credit card
A91: 8470 | B91: I have been trying to cancel my subscription to the Albert app for the past six months. Despite my repeated efforts, the company has continued to charge me monthly without addressing my requests. I attempted to close my account through the app, which requires a XXXX balance in the app 's savings account. However, the app does not function correctly and prevents me from completing the process. Because of this issue, I contacted Albert 's support team multiple times to resolve the problem, but they have not responded to any of my inquiries. This situation has left me unable to cancel my account, stop the recurring charges, or withdraw the remaining balance due to their app 's malfunction. As a result, I feel trapped in an endless cycle of charges with no way to resolve the issue due to Albert 's unresponsiveness and faulty app functionality. | C91: Bank account or service | D91: Nonstandard financial-app subscription/account issue; closest available fit is Bank account or service.
A92: 8472 | B92: Am victim of identity fraud via android bank malware. My chime account was compromised from XX/XX/year> to current Ididnt know til too late that I downloaded a maleware from XXXX play summer XXXX reality, the card data is transmitted to an attacker-controlled XXXX relay server by taking advantage of the built-in XXXX reader built into modern devices . The XXXX XXXX then requests the victim to enter the PIN code with the goal of transmitting the information to the cybercriminal so as to authenticate the transaction. As a result, XXXX establishes a channel between the victim 's physical card ( mine ) and the PoS terminal/ ATM that the cybercriminal is next to, '' XXXX explained. " It allows the cybercriminal to use the victim 's card as if it was in their hands okay and every time I logged into my chime mobile app I gave fraudser complete access. Money was taken and transfer out my XXXX thru all 3 of my account calls to chime been rerouted to ai fake chime customer service center I'm out $ XXXX | C92: Money transfer or service
A93: 8473 | B93: I was told my whole loan would be forgiven. I stopped paying because of that. They harassed myself and my parents every day for 6 months because of " oweing back payments '' which should not have been since the loans should have been forgiven. Consistently asked for paperwork that was never sent. | C93: Debt collection | D93: Loan type is not named, but daily harassment and demands for back payments are collection conduct; Debt collection applies.
A94: 8475 | B94: This complaint is against USAA re : an RV Loan. I made auto bill pay pmts [ {$270.00} - XXXX, XXXX & XX/XX/2023 ] through XXXX Bank, pmts were cashed by USAA, then pmts were re-deposited back into my acct. I was not contacted to let me know of any problem and was not aware of this until end of XX/XX/2023. Also, on XX/XX/2023, I made a telephone transfer of {$1000.00} to my checking acct with USAA, but they applied it to the principal of the loan. I repeatedly tried to call them, but they wouldn't take my calls, because they would try to send me a " secure '' number thru my text, but I repeatedly told them I couldn't receive texts while talking on the phone [ I have a flip phone ]. I am talking about XXXX calls from XXXX thru XX/XX/2023. Now they have started a repossession procedure. XX/XX/2023, I made a pmt. XX/XX/2023 I spoke to a woman who said she would listen to the phone call I made saying how I wanted the {$1000.00} applied and she would send the pmt situation to their legal dept. That was over a month ago and I have received no word as to what is happening. I have not made the XXXX nor the XXXX pmt because I don ; t know what is happening to me and I do not know when I will be homeless. The XXXX pmts are in my savings acct in case I need to catch up, that is if they will allow the # XXXX to go into my checking acct whereby I will be able to make up the back pmts. I want all penalties and extra taken off also. | C94: Consumer loan
A95: 8485 | B95: Eastern Account System. Dear Sir/Madam, I am writing to formally demand that you cease and desist all communication with me regarding the alleged debt referenced under account # XXXX, in according with the Fair Debt Collection Practices Act ( FDCPA ), 15 USC 1692c ( c ). Please note that any further contact from your agency, except for the purpose expressly allowed by law ( such as notification of legal action or final settlement ), will be considered a violation of federal law, and I will take all necessary legal action to protect my rights. | C95: Debt collection
A96: 8487 | B96: Found a student loan debt on my credit report in XX/XX/XXXX, that was opened in XX/XX/XXXX. Loan appears to have been for XXXXXXXX XXXX XXXXXXXX, that is now past due and negatively reported on my credit. I am not nor have I ever been a student at the XXXX XXXX XXXXXXXX, nor do I know anyone who has. I have never applied or received student loan monies from any school. I contacted the collection agency Central Research Inc ( as shown on credit report ) on XX/XX/XXXX, they referred me to the XXXX XXXX XXXX. I contacted XXXX XXXX XXXX on XX/XX/XXXX, filed a ID Theft Affidavit, filed a police report with the XXXX XXXX ( OH ) XXXX XXXX on XX/XX/XXXX, and a filed a report of identity theft with the FTC on XX/XX/XXXX. | C96: Credit reporting
A97: 8491 | B97: I do not know who this company is. I have disputed it with the credit reporting companies. I requested any and all originating documents. It is in violation of HIPAA law as well. Please inform this company to remove in and all information about me from their systems. I did do not consent to any selling or purchasing of any information involving my person. I have never done business with this company. I also will report to XXXX if necessary. | C97: Credit reporting
A98: 8499 | B98: Approxiamately on XX/XX/, I was in the process of purchasing a car from Carvana. I was still inputting information into their system and during that process they kept asking for income verification which I sent several times. XXXX XXXX XXXX XXXX XXXX XXXX XXXX XXXX, I explained to them that I don't use checks and sent them my bank statements. They said that they were having a problem veriying the information. The car purchase was requiring a {$1800.00} down payment that was supposed to be delivered once I had the final approval of the purchase. These folks decided to pull the money from my account while trying to still verify my income and the agent then told me that it was difficult to verify but they took the {$1800.00} from my XXXX XXXX XXXX account without having approved the transaction. It was so stressful that when my phone alerted me that they had taken the funds without me getting the car. It made me upset and told them to cancel the transaction the same day. I asked them why they even took the money before I was given the final approval and I got no response so they said they would cancel the transaction and ensure that I got my money by Monday or Tuesday. That never happened. I am filing this complaint to ask that they not be allowed to take money from anyones account without a confirmed approval of the loan for their vehicles. It is an imconvience for anyone once they take it out and then have to return the funds even when there is no deal. I think they shoudl ensure that the purchaser has a written and verified confirmation of the acceptance of the terms and fudning of the transaction. | C98: Consumer loan | D98: The $1,800 withdrawal arose from an auto-financing/loan approval process; per the Protocol, the loan product controls over the bank-account payment mechanism.
A99: 8505 | B99: Whom It May Concern, I am writing regarding the above-referenced account listed as a charge-off on my credit report. I am requesting full validation of this account. Please provide the following : A copy of the original signed agreement Full payment history Documentation showing I am legally responsible for this debt Proof of your authority to collect on this account Until proper validation is provided, I request that all reporting of this account to the credit bureaus cease. If you are unable to validate the account, please notify the credit bureaus to remove this account from my credit report. Sincerely, XXXX XXXX | C99: Credit reporting
A100: 8528 | B100: The unverified items indicated below continue reporting on my credit report despite several written requests, in violation of federal law. Sections 609 ( a ) ( 1 ) ( A ) and 611 ( a ) ( 1 ) require these items to be authenticated ( A ). I will take legal action against you if you do not validate these items. Please follow the law so that this situation can be settled quickly. XXXXXXXX XXXX XXXX XXXX XX/XX/XXXX XXXX XXXXXXXX XX/XX/XXXX XXXX XXXX XXXXXXXX XXXX XXXX XXXX XXXX XXXX XXXXXXXX XX/XX/XXXX | C100: Credit reporting
A101: 8537 | B101: Our home mortgage was sold by XXXX XXXX to a company called Specialized Loan Servicing LLC on XX/XX/2018. To date we have not received any information or paperwork from Specialized Loan Servicing. Today is XX/XX/2018. Nor has any payment information been sent to us from SLS. I have called to set up payments and SLS will not even speak with me regarding this note which I have authorization to speak on.When I call SLS the call is picked up in a call center in which a person can hear many conversations going on in the background. In this day and age no person wants to speak about their home mortgage in such an atmosphere. I wis to know where I stand legally before we are called late with our payment. | C101: Mortgage
A102: 8538 | B102: I used my XXXX XXXX rewards MasterCard ( Comenity ) to acquire a balance transfer to pay off anothet credit card. On XXXX XXXX my account was charged XXXX . I was charged for the balance transfer but it was not received by my other credit card. XXXX XXXX wrote to me to verify the transfer was unsuccesful and my account would be credited. That was on XXXX XXXX over 60 days ago. I have not been credited and I also paid my other credit card through XXXX off myself. | C102: Credit card
A103: 8539 | B103: Marcus by goldman sachs has my high yield savings accounts. XXXX has my checking account. On a weekly basis, money was being withdrawn from my chase account and being sent to the Marcus account. Three separate checks were sent from chase to Marcus that were never deposited by Marcus. Two ( 2 ) checks in the amount of {$100.00} and one ( 1 ) in the amount of {$500.00}. So the total of {$700.00} was removed from my XXXX account and never deposited in my Marcus account. Further scheduled deposits, after these three checks were sent, were sent and received by Marcus so I filed a dispute. Marcus then withdrew two ( 2 ) checks in the amount of {$100.00} and one ( 1 ) in the amount of {$500.00} from my savings account and issued me a check. The check they issued me could not be cashed so I am now down the {$700.00} withdrawn from my chase account and {$700.00} withdrawn from my Marcus account. I made new accounts with Marcus and put locks that no further withdrawals should be made from my existing Marcus accounts. Further withdrawals were made and then my entire Marcus account has been locked. So now I am down {$1400.00} and can not log into my account to access any of the funds in my savings account. I called immediately when I found out my account is locked to find out why and how long and they said 7-10 business days. It's been over three weeks and they have not given me any updates about how to unlock my account and access my funds. They have all of my money and are not letting me access it despite the dispute only being about {$700.00}. | C103: Money transfer or service
A104: 8549 | B104: I had bought a TV from Walmart and the 3rd party company XXXX with my Capital One Bank Card. The thing is that I want to return the merchandise do to being the wrong TV. I contacted Walmart and Capital One to open dispute and return the item. Capital One told me to wait for XXXX XXXXs to contact me within 48 hours and that they was a case XXXX XXXX. That they were going to fix the issue. I have been emailing the 3rd because they never called or send me the label for the return. Now Capital One tells me that the case is close and all I am asking is for a refund and return TV. XXXX XXXX told me that the case was close as well, they never called or emailed me back. Need to know if something can be done. | C104: Credit card
...

Sheet Labeler 2
A1: row_id | B1: narrative | C1: your_category | D1: flag_note (if forced/hard fit/general comments)
A2: 8022 | B2: I applied for a bank account with XXXX on XXXX XXXX and was declined stating there were discrepancies on my XXXX report. I knew that had to be an error because i filed for bankruptcy and every creditor was ordered by the judge to CEASE AND DESIST. I filed chapter XXXX bankruptcy with case XXXX FL on XX/XX/17 and the case was discharged in XX/XX/2017. However, XXXX XXXX is STILL REPORTING EVEN AFTER MY BANKRUPTCY. Each creditor is subject to up to {$1000.00} fine for violation of fair credit reporting act. Chapter XXXX bankruptcy discharges all debt! | C2: Credit reporting | D2: Bank account denial is the trigger, but complaint is post-bankruptcy reporting
A3: 8024 | B3: I fell victim to a multilayered scam operation orchestrated by XXXX ( XXXX ) ( the Company ) with the design, development, manufacturing, promoting, marketing, distributing, labeling, and/or sale of illegal and outright fraudulent investment services, all of which aim at contributing to the goal of robbing and defrauding clients through a predetermined cycle of client losses to gains in the equivalent of XXXX USD which was transferred from my wallet utilizing Coinbases services. | C3: Money transfer or service
A4: 8033 | B4: I have been a longstanding customer with Chase Bank, maintaining multiple credit card accounts with them over a period of several years. I have always managed my accounts responsibly, making timely payments and adhering to all the terms and conditions. To my knowledge, I have not violated any rules or engaged in any behavior that would warrant account closure. Recently, I discovered that Chase had closed all of my credit card accounts without prior notice or explanation. I received no warning or notification regarding any issues with my accounts. Upon noticing the closures, I immediately contacted Chase customer service to inquire about the reason behind their decision. Despite multiple attempts and speaking with several representatives, Chase refused to provide any specific reason for the closures. I was told that they were unable to disclose why the accounts were closed and that the decision was final. I was not given any opportunity to appeal or resolve any potential issue that may have prompted this action. This sudden and unexplained closure of my credit card accounts has caused me significant inconvenience and concern. It has impacted my credit utilization ratio, which may negatively affect my credit score, and I am now left without access to credit that I previously relied on for regular financial activities. I believe that as a consumer in good standing, I am entitled to a clear explanation for the closure of my accounts. The lack of transparency and unwillingness to provide any justification is deeply troubling and potentially unfair. I am requesting that the CFPB investigate this matter and help facilitate a response from Chase that provides a clear and detailed explanation for their actions. | C4: Credit card
A5: 8044 | B5: My husband and I open a personal loan through OneMain. The company was originally named SpringLeaf. The loan was paid in full XXXX XXXX, 2017. I tried to obtain an letter from the company stating this loan was paid in full ; so I could provide it to the three credit bureaus ; but, was unsuccessful. Attached will be a summary printout from the local office and a statement printout providing {$0.00} balance. Even though these statements are acceptable to me ; there are not acceptable for the three credit reporting bureaus. Would you please assist me with this matter? Thank you | C5: Consumer loan
A6: 8050 | B6: Cypress Collections Professional Collection Agency XX/XX/XXXX XXXX XXXX XXXX XXXX, CA XXXX Re : Reference # XXXX Client # XXXX Thank you for your inquiry. I do in fact dispute the claim of {$120.00} plus the additional interest that was erroneously billed to me and certainly, your threats to damage my credit worthiness. I am a Veteran under the care of the Veterans Administration at XXXX XXXX. I have communicated with Doctors on Duty and have told them that their claim needs to be filed with the Veterans Administration. I also told Doctors on Duty that I would talk to the VA regarding the erroneous billing for my approved office visit. I talked to my primary care doctor at the VA and was told that there is a record of an authorized request for medical service on XX/XX/XXXX. Initially I told this to Doctors on Duty bookeeper. I clearly told the Doctors on Duty staff that the VA sent me and that I needed to be evaluated for XXXX because of XXXX XXXX and that I was a veteran. The reason for this going to collection is clearly not my doing. It is in fact Doctors on Duty responsibility to bill the VA as per their contract ( a requirement that they did not do ) Embroiling me in their mishap with a threat of affecting my credit worthiness is disturbing at best. I have contacted the Community Provider division of VA and have filed an Adverse Credit Report - XXXX. Cypress Collection as well as Doctors on Duty have been notified to cease and desist their illegal claim. If in fact my credit worthiness is affected, I will sue for defamation of character and elder abuse of an ailing veteran. I am willing to pursue a course of action against both Doctors on Duty and Cypress if this persists any longer. I defended my country with dignity and courage and expect respect and thanks for my service, rather than being threatened and abused by Doctors on Duty and Cypress Collections. Thank You XXXX cc : FTC www.ftc.gov cc : Senator XXXX XXXX | C6: Debt collection | D6: Debt collection because nothing has been reported to a credit bureau yet. The credit damage is only a threat.
A7: 8053 | B7: I was shocked when I reviewed my credit report and found late payment on the dates below : XX/XX/2018- 30 DAYS LATE I am not sure how this happened, I believe that I had made my payments to you when I received my statements. My only thought is that my monthly statement did not get to me. | C7: Credit reporting
A8: 8060 | B8: I've recently received a copy of my credit report and noticed several inaccuracies and unauthorized accounts/information reporting to my credit report. These remarks have been detrimental to my life and credit health. CAPIO PARTNERS LLC {$3100.00} XX/XX/year> | C8: Credit reporting
A9: 8062 | B9: I am submitting this complaint regarding Credit Karmas refusal to update my legal name on their platform, despite my repeated efforts and full compliance with their documentation requirements. I legally changed my name and have already updated it with the XXXX XXXX XXXX and on my government-issued ID. I contacted Credit Karma to request that they update my account to reflect my correct legal name. As requested, I submitted a copy of my government-issued ID and Social Security card , both showing my current legal name. Despite providing this documentation, Credit Karma has refused to update my account. Their support team has not given a clear or valid reason for this refusal, nor have they offered any alternative solution. This failure to update my name has caused confusion and concern, especially as Credit Karma continues to pull and report credit information under a name that is no longer legally mine. I am concerned that this may impact the accuracy of my credit file and hinder my ability to manage my financial accounts effectively. I believe I have made every reasonable effort to work with Credit Karma, and I am now requesting assistance from the CFPB to resolve this matter. I am seeking that Credit Karma update my name in their system in accordance with the legal documentation I have provided and that they ensure all associated credit reporting is accurate. | C9: Credit reporting | D9: Credit Karma name update - not a CRA strictly
A10: 8071 | B10: Upon termination of my lease in XXXX I was assessed a disposition fee above the contractual obligation. In investigating this fee I had discovered that XXXX XXXX was charging for hail damage to the vehicle. This vehicle never experienced a hail storm while in my possession. The process of contacting XXXX XXXX XXXX XXXX and disputing the charge took costly time. Once the determination was made by a XXXX representative that I was indeed not responsible for any additional charges, as there was no hail damage, I immediately paid the remaining disposition fee. I had never been late in a vehicle payment to XXXX or any other automotive debtor. Because of the time it took XXXX XXXX to investigate and correct this charge I was outside of my 30 day payment window. They they reported me to the 3 bureaus as having a late payment. I sent my formal request to have the negative marks removed from my credit report at the 3 bureaus ; XXXX, XXXX, and XXXX. I submit this request on authority from the representatives at XXXX. I included a brief statement on what had happened and a copy of my credit report. On XX/XX/XXXX I received a letter from XXXX XXXX saying their reporting was correct. I called on XX/XX/XXXX to take further action. At this point I was informed I could make another formal dispute but could not actually speak with anyone who makes the decisions. A customer service rep by the name of XXXX and his supervisor XXXX were quite unwilling to help. I just want the negative mark removed from my credit. I am currently not obligated with any further debt to XXXX XXXX. | C10: Credit reporting | D10: Lease disposition fee led to late mark; complaint is removing it
A11: 8074 | B11: I am writing to request an investigation of the following information that appears on my Early Warning Systems consumer report, which I believe to be fraudulent. In accordance with the Fair Credit Reporting Act, I assert that the list of accounts below has violated my federally protected consumer rights to privacy and confidentiality under 15 USC 1681. These items listed above have violated my rights as outlined in 15 U.S.C. 1681, Section 602 A, which grants me the right to privacy. 15 U.S.C. 1681, Section 604 A, Section 2 also states that a consumer reporting agency can not furnish an account without my written instructions. Furthermore, 15 U.S.C. 1681c ( a ) ( 5 ) stipulates that no consumer reporting agency may include any adverse items on a consumer report if they predate the report by more than seven years. Additionally, 15 U.S.C. 1681s-2 ( a ) ( 1 ) specifies that no information can be furnished to a consumer reporting agency if the person knows, or has reasonable cause to believe, that the information is inaccurate. I have NEVER opened or used the following account numbers, and I request that all information related to these accounts be removed immediately : Bank : XXXX XXXX Incident Date : XX/XX/year> Contribution Ref # : XXXX Account # : XXXX ABA Number # : XXXX Additionally, I do not recognize the following inquiries that appear on my report. I am a victim of identity theft, and I do not recognize the following inquiries. I request that the following inquiries be removed from my Early Warning Services consumer report immediately : | C11: Credit reporting | D11: Early Warning Services (specialty CRA) report
A12: 8094 | B12: On XX/XX/XXXX an online transaction was made through our banking institution Wells Fargo via XXXX in the amount of {$230.00}. XX/XX/XXXX XXXX TO XXXX XXXX ON XX/XX/XXXX REF # XXXX {$230.00}. The product/service was not received. Contacted Wells Fargo and a claim was filed # XXXX. We would like our money back. This was fraudulent act committed ; Wells Fargo should back all transactions on their website and in good faith refund the customer. We were told most likely we would not be getting our funds back. Please assist in obtaining our {$230.00} back. Thanks. | C12: Money transfer or service | D12: Payment via WF + unnamed service (likely P2P) for undelivered goods; BA plausible
A13: 8095 | B13: On XX/XX/XXXX/XX/XX/XXXX my debit card was stolen while on a work trip in XXXX, New York In addition it was my contention that the thief was able to get my PIN. That thief, used the card throughout the XXXX XXXX XXXX area, charging up almost {$3000.00} dollars at 30 various different drug stores over a 3 hour period, making cash back purchases in small increments on average of {$50.00} dollars. I reported the fraudulent charges to the bank as soon as I became aware, as did my wife who is joint on the account. I filed a police report in XXXX XXXX XXXX and XXXX XXXX, CA, my place of residence. Upon review the bank rescinded the credits to my account and stated their judgement was based upon inconsistencies with my and my wife 's statements. As i mentioned to the back, I was not aware of how it was stolen, but merely giving them suggestions on who might have been the perpetrator. The bank investigators did n't not put forward a good faith effort to follow up on this claim, nor did the bank hold up their fiduciary responsibility to protect my debit card from this clear fraud while it was happening. Furthermore, while I still have an active police investigation, the bank has already rendered judgement. This matter will be resolved in civil court if I ca n't get the protection of the Bank in regards to my FDIC protected money. I wish to report the bank, the claims department and its management for gross negligence in this matter and I hope the CFPB can help me gain protection from a banks disregard for its primarily responsibility to protect my money | C13: Bank account or service
A14: 8096 | B14: An unauthorized transaction was made on my Chime XXXX XXXX account on XX/XX/year> in the amount of {$1400.00} at XXXX XXXX. I transferred funds to my account to set aside for a moving fund. I filed a dispute with Chime on XX/XX/XXXX they then denied my claim the following day without proper investigation. An appeal or rebuttal was filed on XX/XX/XXXX at which point I also provided a written statement and a statement from the business stating the charge was unauthorized. That rebuttal was also denied despite submitting substantial information. I tried calling police but because I was unsure where I misplaced my credit card they were unwilling to file a dispute. It has been now almost XXXX months of me fighting the bank and nothing has been returned to me and this issue has yet to be resolved. | C14: Bank account or service | D14: Chime account; narrator also mentions 'credit card'
A15: 8097 | B15: I have notified Experian, XXXX and XXXX several times regarding the XXXX XXXX account. XXXX XXXX is refusing to discuss collection for XXXX account or accept any payments from me stating they are no longer handling account it is with a 3rd party. The is no other company reporting this account to my credit report, only XXXX XXXX. I have attempted several times to resolve this account with XXXX XXXX with the latest being today XX/XX/2021 at XXXX eastern, I spoke with XXXX whom once again refuses to discuss account, accept payment or even send a current dated bill for the balance owed. I have recorded conversations of XXXX XXXX refusals. I have filed several disputes advising Experian, XXXX and XXXX of the issues with XXXX XXXX and the recorded conversations with contact information to reach me to hear them. All 3 continue to close my disputes stating they verified account details without investigating the issue Im disputing. XXXX XXXX should not be allowed to remain on my credit report if they are refusing to discuss account, accept payment for account or even send me a current bill for account. At this point Im ready to get a lawyer and sue Experian, XXXX, XXXX and XXXX XXXX because Ive tried for several months to resolve this myself to no avail. | C15: Credit reporting | D15: Creditor refuses payment, but ask is CRA dispute/removal
A16: 8098 | B16: I am submitting this complaint due to a judgment and wage garnishment related to a charged-off XXXX account. I was never properly served with notice of the original lawsuit and only became aware of the judgment after receiving notice that my wages would be garnished. I did not live at the address sworn to be served at. I have attached my lease for the time frame in question. I filed a Motion to Strike the judgment on the grounds of improper service, but it was denied. The debt collector has not provided a valid affidavit or proof of service that complies with state law requirements. I believe this violated my due process rights. Additionally, I never received a proper debt validation or breakdown of the amount allegedly owed. The debt was originally charged off by XXXX, and I do not have confirmation that the current party attempting to collect has the legal right to do so. I am requesting the following from the CFPB : An investigation into whether proper service of process was completed before the judgment was granted. Confirmation that the entity pursuing the garnishment is authorized to collect on this debt. Full validation of the alleged debt, including the original contract, chain of assignment, and accounting of charges. I believe this judgment and garnishment may have been obtained unlawfully and am requesting assistance in having it vacated if violations occurred. Thank you for your attention to this matter. | C16: Debt collection
A17: 8106 | B17: My mortgage loan originated XX/XX/XXXX. In XXXX, I applied for a home made affordable loan modification but was denied. Wells Fargo informed me that I could do a short sale. My realtor submitted several offers to them for a short sale and they refused them and proceeded to foreclose on the property in XX/XX/XXXX. On XX/XX/XXXX, I contacted Wells Fargo 's Enterprise Complaints Mgmt Office letting them know that I felt my home had been wrongfully foreclosed and was given a case number and assigned a representative. XXXX XXXX is my Case SpecialistXXXX XXXX XXXXXXXX. I have received four different letters stating they need more time to finalize their research. I feel they are are not taking the situation seriously. I was told that another letter is in the mail stating that they should complete their work by XX/XX/XXXX. That will be two months from the date that I reached out to them. | C17: Mortgage
A18: 8108 | B18: I last spoke with a supervisor ( XXXX ) on XXXX after receiving the last response from a Citibank Representative on my recent complaint with CFPB. Although, I did not inquire about " settling '' the account I was not given any options on how to resolve the balance either. Currently, the principal balance according to XXXX is {$590.00} with {$170.00} ( late fees of {$25.00} per month ) plus any interest. Prior to the conversation with XXXX, a conversation ( early XXXX ) with a representative in the loan department stated that " for two payments ( XXXX and XXXX ) no interest would be charged and the account would be deferred. '' I would not need to make any payments. But, I made a payment in XXXX in the amount of {$250.00} ( {$220.00} is the minimum payment ). XXXX refused to provide any options on how to resolve the matter. I asked about waiving a few fees, to which were immediately dismissed by saying '' we can't do that because you were consistently late. '' Which I felt was extremely offensive, I felt like a criminal in that moment. In XXXX of last year, I lost my job which put me behind in payments. But I paid what I could. Now I am a product of the Pandemic, but I am still paying trying to resolve this responsibility. I was so angry by her statement that I responded back stating " I could easily let the account go and not pay anything! '' My experience with Citibank has been an extremely horrible ordeal. It is unfortunate that I stayed this long, over 10 years. | C18: Credit card | D18: Citibank; 'loan department' mentioned but minimum payment/late fees indicate card
A19: 8118 | B19: I am filling a complaint against Cash App ( Block INC. ) due to inadequate customer service and unfair practices, which violate the Consumer Financial Protection Act. Specifically, Cash App failed to take timely and effective measures to prevent and address fraud on their platform, leaving my account vulnerable and unprotected. Furthermore, their dispute resolution process was unfair and deceptive, as they did not comply with Electronic Fund Transfer Act and Regulation E. These actions have caused significant inconvenience and financial loss and i seek appropriate redress for these violations | C19: Money transfer or service
A20: 8122 | B20: I am filing this complaint regarding a medical collection account being reported on my consumer credit reports by Aargon Agency , Inc . This account is inaccurate, unlawfully reported, and should be immediately deleted for the reasons outlined below. First, I never authorized the original medical provider or any third party to disclose my protected health information ( PHI ) to this collection agency for the purpose of credit reporting. The reporting and furnishing of this account necessarily involves the disclosure of sensitive medical information, which I did not consent to. This appears to be a violation of the Health Insurance Portability and Accountability Act ( HIPAA ) and its privacy protections regarding unauthorized disclosure of medical information. Second, this account has been reported to the consumer reporting agencies without proper validation and without a permissible purpose, in violation of the Fair Credit Reporting Act ( 15 U.S.C. 1681 et seq. ). I dispute the accuracy, ownership, and legal authority of this collection account. The furnisher has failed to demonstrate that it has the legal right to report this alleged debt or that the information being reported is complete and accurate. Additionally, medical collections are subject to heightened accuracy and privacy requirements. The continued reporting of this account is causing ongoing harm to my credit profile and financial well-being. I am requesting that the CFPB require Aargon Agency, Inc to : Immediately delete this medical collection account from all consumer reporting agencies Cease any further reporting or disclosure of my medical information Provide written confirmation that this account has been permanently removed If this matter is not resolved promptly, I reserve all rights to pursue further complaints with the Office for Civil Rights ( OCR ) for HIPAA violations and any additional legal remedies available to me. | C20: Credit reporting | D20: Medical collection; HIPAA angle but ask is deletion from reports
A21: 8125 | B21: The company currently servicing our mortgage reached out in XX/XX/XXXX to refinance our mortgage due to the low rates, so we agreed. We locked in a rate of 3.125 % on XX/XX/XXXX with NewRez and supplied them with all the upfront requested documentation and eSigned all necessary forms. It is now XX/XX/XXXX and we still have NOT closed on the refinanced loan and they are asking for more documents, and my husband to correct the figures multiple times on the documents provided by NewRez for the refinance ( incorrect escrow figure, property taxes, etc. ). We constantly reached out to the company throughout the multitude of months since starting the process in XXXX and were told various stories about how the loan would be underwriting soon once one more bit of information was verified -- and the information to be verified never was accurate to begin with for our loan. Or, there would be no response and no escalation even after we demanded status updates with set deadline dates for such information. We have lost out on four months of saving {$300.00} a month that the refinance should have secured had it closed at the end of XX/XX/XXXX as it should have closed, and we now can not refinance with an alternate company at the same rate as rates have now increased, and also, the loan office does not get paid until this loan closes so there are multiple parties effected by this company 's gross incompetence. | C21: Mortgage
A22: 8128 | B22: Kia Motor Finance has a deferment program which I applied for and instead of them trying to help me they refuse to - my loan will be 60 days late by the XXXX of this month and they will not help - they say they will approve you and then tell you that there is a document that you need to sign and send back however in the meantime they do not sent the document and this will impact my credit - they are not being helpful at all. | C22: Consumer loan | D22: Kia > auto
A23: 8129 | B23: Have filed multiple different disputes with Equifax for an account on my credit with XXXX XXXX XXXX that was opened under fraud. Each time there is no resolution, the account continues to show up on my report causing me to lose time by filing disputes and delay any credit related purchases that I may have. XXXX and XXXX have both already removed the account without delay. Complaints have already been filed with the FTC and Equifax still will not take action. | C23: Credit reporting
A24: 8130 | B24: I am stressed out because this company is violating my rights Under 15 U.S.C. 1681s-2 ( a ), data furnishers are required to report only accurate and complete information.Reporting unverifiable or inaccurate data is a violation of federal law. | C24: Credit reporting
A25: 8136 | B25: I did apply for the card but never finalized that I wanted because it was only for {$300.00} and they take {$80.00} of that for fees etc so I didn't want it and never confirmed that I wanted the credit card ... I don't even have the card in my possession... | C25: Credit card
A26: 8142 | B26: I attempted to withdraw money from my account to another bank account in my name. Marcus froze the funds and claimed that they needed onerous documentation from me ( a statement from my other bank sent to them via mail ) in order to complete the transfer. They also could not manually reverse the transfer, leaving my $ XXXX in limbo while Marcus decides what to do with the funds at their sole discretion. | C26: Money transfer or service
A27: 8166 | B27: I sold an item and shipped it via USPS Media Mail to a buyer named XXXX XXXX. She filed a PayPal dispute claiming she never received the package. This was false. She refused delivery and had the package returned to sender. I have the returned package in hand with a USPS label clearly marked " Return Postage Due = {$5.00} '' dated XX/XX/year> and stamped " Refused. '' Despite my evidence, PayPal ruled in her favor. The fraudulent dispute resulted in a {$19.00} reversal against me, plus I was charged {$5.00} in return postage caused directly by her refusal. Total loss : {$24.00}. I am requesting PayPal reopen and reverse this decision. | C27: Money transfer or service
A28: 8168 | B28: The credit bureaus must obey many laws, including the Fair Credit Reporting Act ( FCRA ). And according to the FCRA insert condition such as an incorrect balance an incorrect account number an undated late pay a missing field of missing field here such as status the wrong account type an incorrect a late pay after account was closed an inaccurate date of last activity an inaccurate date of last update a charge off listed as open a collection account with an inaccurate reporting dateLEAD BANK self XXXX POTENTIALLY NEGATIVE MONTHS Credit usage 0 % account Balance updated XXXX XXXX, XXXX Credit limit {$1000.00} Account info Account number XXXX Open/closed Closed Date opened XX/XX/XXXX Account type Revolving PAID CHARGE OFF VARIABLE RATE. PAID CHARGE OFF VARIABLE RATE. XXXX # XXXX Open/closed Closed Date opened XX/XX/XXXX Account type, Account, XXXX, XXXX Installment reported late payment XX/XX/XXXX XXXX XXXX XXXX XXXX PAYMENT Balance {$0.00} Balance updated XX/XX/XXXX, | C28: Credit reporting
A29: 8174 | B29: Our mortgage company 's loss/draft department are solely to blame for our issue. Not the insurance company or the VA. We had a catastrophic loss of our home and we have cooperated with everything they have asked, but they do not give us the funds we need and have paid out of pocket and taken from our retirement savings, at a heavy tax levied against us, and our personal savings. We had difficulty getting a contractor to over see the work. Our last contractor did nothing for 8 months. Nothing. So we became our own general contractor and got our permits and hired the sub contractors. I am attaching some of the emails we have written. So far we have asked for reimbursement from two contractors for the final completion of the exterior of the house and the excavation company that worked to remove the old burned house and dig/fill utility trenches, and prepare the ground for radon barrier and concrete pour. They did reimburse at least once for our underground plumbing work and the builder completing the outer shell of the house. We have been waiting for 4 weeks for them to pay the final bill to that company. | C29: Mortgage
A30: 8180 | B30: Subject : Repeated Account Closures After Approval Request for Explanation I am submitting this complaint regarding a pattern of behavior by Capital One that I believe may constitute an unfair or deceptive practice. Capital One has repeatedly approved my applications for credit cards, only to close the accounts shortly afterward citing a vague business decision without providing any meaningful explanation. This has occurred multiple times. Despite these closures, Capital One continues to solicit and approve new credit card applications for me. This creates a confusing and frustrating situation where I am led to believe I am eligible for their products, only to have the accounts closed again shortly after opening. I have no negative payment history with Capital One and have complied with all account terms. Because these approvals are being granted and then reversed repeatedly, I am concerned that this process may result in unnecessary hard inquiries on my credit report and, in some cases, the collection of annual fees before the account is closed. At this point, I am requesting that Capital One provide a clear explanation addressing the following : 1. Why my accounts continue to be approved and then closed shortly thereafter. 2. Whether I am internally flagged or otherwise deemed ineligible for Capital One credit products. 3. Why I continue to receive solicitations and approvals if the bank has no intention of maintaining a credit relationship with me. If Capital One has determined that I am not eligible for their products, I respectfully request that they cease marketing and approving applications for credit cards in my name. I am simply seeking transparency and fair treatment in this matter. Thank you for your attention to this issue. | C30: Credit card
A31: 8184 | B31: I have a a few loans with RISE. Last month when I looked at my credit report I had XXXX inquiry from this company now I have XXXX and they all are dated for different months in the same year. I understand that the company will pull my credit to approve the loan, but they can not place the inquires on the file 10mos after the loan has been paid off. | C31: Credit reporting
A32: 8203 | B32: I am filing a complaint against Cash app ( Block, Inc. ) due to inadequate customer service and unfair practices, which violate the Consumer Financial Protection Act ( CFPA ). Specifically, Cash App failed to take timely and effective measures to prevent and address fraud on their platform, leaving my account vulnerable and unprotected. Furthermore, their dispute resolution process was unfair and deceptive, as they did not comply with error resolution requirements under the Electronic Fund Transfer Act ( EFTA ) and Regulation E. These actions have caused significant inconvenience and financial loss, and I seek appropriate redress for these violations. | C32: Money transfer or service | D32: Generic Cash App/Reg E template
A33: 8206 | B33: In XX/XX/2021, our mortgage payment was {$1500.00} instead of the normal {$1100.00}. I paid it and thought it was the difference for insurance. XXXX came around and it was high again. After tons of call and inquiring, they filed my property tax incorrectly. I got the necessary paperwork to them. They told us to use the 15 day grace period to allow them to correct the numbers and pay our mortgage. They say we will owe {$1500.00} this month. We should get a lower payment plus last months overpayment reimbursement. Ive called 29 times. Ive been told to shut up, Ive been hung up on 5 times. I get told different things every time. No one knows what to do or how to help. They just say pay the {$1500.00} and they will fix it. I need to know what happened to the {$600.00} escrow check they sent out, when it will be fixed, and to be certain it wont reflect on my credit score. Most unprofessional company Ive ever experienced. | C33: Mortgage
A34: 8207 | B34: Money was XXXX or XXXX from XXXX XX/XX/XXXXXXXX where I received my Direct Deposit Payroll, to XXXX XXXX XXXX XXXX XX/XX/XXXX The intent was to buy some shares of XXXX, since they are a Stock/Trading company. My deposit is not there. They can't find it. Initially I was given an availability date of XX/XX/XXXX then 2 days later it was changed to XX/XX/XXXX, which I clutched my pearls, and thought that was kinda a long time to hold one 's funds! : ( Why did the dates change twice, & now my funds are " stuck '' somewhere, waiting to be processed!? Chime says the didn't receive the REJECTED funds back yet that XXXX admitted to rejecting. I talked to a Gentleman named XXXX at XXXX who explained this unfortunate latest update to me! | C34: Money transfer or service | D34: Transfer to brokerage lost in transit
A35: 8213 | B35: I have a loan with United Wholesale Mortgage. I have not been able to reach ANYONE from customer service I had an insurance rep call me with the same problem trying to reach them They do not answer the phone and do not acknowledge even having my loan, and however long i try or whatever phone number i try reaching customer service on it just does not go through. | C35: Mortgage
A36: 8215 | B36: I have submitted multiple disputes regarding these accounts that is reporting inaccurately on my credit report. I have also submitted multiple reports regarding the account that needs to be updated These companies have refused to do work on disputes even though they're required by the law to do so. Account Name : XXXX | C36: Credit reporting
A37: 8222 | B37: I received an email that my account was closed at XXXXXXXX XXXX XXXX on XX/XX/year>, with no stated reason. Since this email, my account is restricted and I am unable to access {$3300.00} in my account. | C37: Bank account or service | D37: Institution redacted; account closure/funds restricted
A38: 8225 | B38: XXXX & Equifax are reporting an erroneous collection on my credit report for XXXX XXXX XXXX - XXXX - I never received one notice regarding this debt, it just showed up on my credit report. This was paid | C38: Credit reporting
A39: 8244 | B39: According to 15 use 1681eb Everything must be 100 percent max accurate The credit bureaus keep disrespecting the laws. I showed them multiple times of how they are violating the Fair Credit Reporting Act. According to 15 use 1681 ( 5 ) The credit bureaus said everything was complete and accurate and I asked them how if the open date is wrong. Then I ask them to provide me description of the investigation according to 15 USC 1681 ( 7 ) and they never did. I have proof of my letter for that. Also according to 15 USC 1681 s-2 A person shall not furnish any information relating to a consumer to any consumer reporting agency if the person knows or has reasonable cause to believe that the information is inaccurate. This is violation after violation after violation. This is causing me stress because I have no hope with this system | C39: Credit reporting
A40: 8245 | B40: I am writing to formally contest the inclusion of fraudulent account in my Experian credit report. Despite submitting a dispute letters and the required documentation to the Federal Trade Commission ( FTC ), as per your guidelines, this account persist on my Experian report. After uncovering this fraudulent account, I contacted the relevant bank, which acknowledged its fraudulent nature and assured me of its removal from their records. Subsequently, XXXX and XXXX have both expunged this account from their records after verifying its fraudulent status. I am puzzled as to why Experian continues to report this fraudulent account, especially since the other credit bureaus have already removed it. I have completed all necessary steps and furnished all relevant documentation to substantiate my claim of identity theft. I hereby request a comprehensive investigation into this matter and the immediate removal of this fraudulent accounts from my Experian credit report. The bank has confirmed the fraudulent nature of this account, and its persistence on my credit report is unjustified and detrimental to my creditworthiness. XXXX XXXX XXXX XXXX XXXX XXXX XXXX XXXX XXXX XXXX XXXX | C40: Credit reporting
A41: 8248 | B41: I used Moneygram on XX/XX/XXXX to send XXXX usd. And i git a messsage saying the money was sent with the reference number XXXX, but minutes after i got an email saying the opened a case XXXX. They lied because they said it was the receivers bank problem and i told them many times that we spoke with the branch manager ( XXXX bank ) and they are very opened to receive the money so we drove many times to the branch wasting money and time. Please we need our money back because we have so many things to pay for. XXXX XXXX XXXX XXXX | C41: Money transfer or service
A42: 8250 | B42: Request for Update to Paid As Agreed Never Late ( PAANL ) Violation of 15 USC 1637b To Whom It May Concern : I am writing to formally request an update to my credit report regarding my account with : 1 ) XXXX XXXX XXXX XXXX XXXX to the provisions of the Truth in Lending Act, specifically 15 USC 1637b, a creditor may not treat a payment on a credit card account under an open-end consumer credit plan as late for any purpose unless the creditor has provided the required notice, as outlined in section 1637b. Section 1637b of the Truth in Lending Act clearly states that a creditor must inform the consumer in writing, within a reasonable period, if a payment has not been made within the grace period. Specifically, if a payment is considered late, it must not be treated as such unless the creditor notifies the consumer at least 21 days prior to the due date. As of today, I have not received any such notice regarding the account referenced above, nor have I been notified of any payment being considered late. In light of this, I am requesting that my account be updated to reflect the accurate status of " Paid As Agreed Never Late '' ( PAANL ) as no late payments were reported or properly documented. Since no notification of a late payment has been issued in compliance with the law, my account status should accurately reflect that it was paid on time and as agreed. I request that you update my credit report accordingly and remove any negative reporting related to this account. I expect a response within 30 days, as required by the Fair Credit Reporting Act ( FCRA ), and would appreciate your prompt attention to this matter. If you need any additional information or documentation to process my request, please do not hesitate to contact me. I appreciate your cooperation in ensuring that my credit report is accurate and complies with all applicable laws. Sincerely, XXXX XXXX | C42: Credit reporting
A43: 8251 | B43: XX/XX/XXXX Subject : Dispute of Inaccurate Late Payment Reporting on Account # XXXX Dear CFPB, I am writing to formally dispute inaccurate information being reported on my credit file regarding the XXXX account ( # XXXX ). According to the Fair Credit Reporting Act ( FCRA ), you are required to ensure the accuracy of the information reported and to investigate disputes promptly. Upon reviewing my credit report, I found that the payment status for this account continues to indicate " 30 days late, '' which is inaccurate. I have consistently made on-time payments for this account, and I have attached relevant documentation to support this claim. Here are the details of the account : High Balance : {$2000.00} Date of Last Activity : XX/XX/XXXX Date Reported : XX/XX/XXXX Date Opened : XX/XX/XXXX Balance Owed : {$0.00} Closed Date : Not Available Account Rating : Paid Account Status : Closed Payment Status : Late 30 Days Creditor Remarks : Consumer disputes- reinvestigation in progress ; Closed or paid account/zero balance Two-Year Payment History : Indicates " OK '' for all months but continues to show a " 30 Days Late '' status inaccurately. I request that Equifax provide a detailed description of the investigation procedure conducted to verify this account 's payment history, as required under 15 USC 1681i ( a ) ( 7 ). Furthermore, I request documented evidence supporting the late payment claim, including specific dates, amounts, and correspondence that validate this reporting. In the absence of valid evidence, I demand that the payment status for this account be updated to " Paid As Agreed Never Late '' immediately. Failure to comply with this request within the 30-day timeframe outlined in the FCRA will constitute a violation of my rights as a consumer. Thank you for your prompt attention to this matter. I look forward to your response and resolution. Sincerely, XXXX XXXX XXXX XXXX | C43: Credit reporting
A44: 8257 | B44: Navy Exchange ( NEX ), the " XXXX '' onboard US XXXX bases, offers currency exchange for personnel stationed overseas ( in XXXX ) to pay their off-base rent. However, the exchange rate offered is always 2-3 % less than the Bank Rate for US dollar to XXXX XXXX exchange. To offset this, the Navy Exchange provides a {$10.00} gift card for use at the NEX, for each month paid. However, this is inequitable because the gift card is always for the same amount, regardless of the monthly rent amount ... so a single military member with an $ XXXX/month ( equivalent ) rent payment derives more proportional benefit from this {$10.00} gift card than a military family whose rent could be closer to $ XXXX ( equivalent ). | C44: Money transfer or service | D44: Military currency exchange rate - forced fit
A45: 8263 | B45: Debt Collector ( s ), Obligors, Debtors XXXX and XXXX XXXX are attempting to collect an alleged debt of the Consumer. The named debt collectors are engaged in illegal acts by simulating a judicial court affiliated with the United States. The debt collectors were served numerous notices under federal consumer statutes but fail to comply. The debt collectors are attempting to seize the private property, consumer goods of the Consumer under the guise of Foreclosure which is not being performed in a competent judicial district under 15 USC 1692i. The debt collectors are not exempt pursuant to XXXX, XXXX under federal law. This debt collector is taking illegal non judicial actions in violation of the FDCPA, 15 USC 1692, Identity Theft, XXXX. The FTC has a report by the consumer. | C45: Debt collection
A46: 8264 | B46: Hello, I got asked to create a song. They offered to pay me XXXX but sent XXXX on " Accident ''. I deposited the check into my wellsfargo account the XXXX of XX/XX/2021. The check cleared and was in my account, so I sent them 4 payments of XXXX, only to have that check bounce 3 days later. I wouldnt sent them any money if the check wouldn't of cleared. I didn't get any notifications that it could be a fake check. I didn't have any pendings over the check it was all in my account. The account the contacted me was through XXXX, this is the account. XXXX The email address the check came from is XXXX Hope this information helps! | C46: Bank account or service
A47: 8270 | B47: I had a credit card account with chase bank the was closed due to payment issue. But i paid down full amount on the time. My credit score is outstanding im trying to apply for a credit card with chase and its denying. | C47: Credit card
A48: 8274 | B48: I am unemployed seeking employment and I have been denied employment because of the fake news contained in my credit file. There are numerous inquiries that I have never engendered and I've never even heard of these companies. There are fake telephone numbers on my credit file I have never had, there are fake address to places where I've never lived too. My credit file with Experian contains a lot of fake news. The information contained in the credit file belongs to the consumer and if it is inaccurate or contains misleading information, the consumer has the right to correct the information. While I was legally XXXX for XXXX, my identity was stolen from me and I took appropriate action notified the Credit Reporting Agency ( CRA ) in this complaint with a Fraud Affidavit and proof of legal incapacity. I notified federal law enforcement. The CRA in this complaint told me to contact all the companies. I did. I notified the companies that inquired on my credit file to remove and/or correct the erroneous information from my credit file. They all told me that the CRA does that, not them. I then wrote the CRA in this Complaint that I've already spoken to the various companies that inquired in my credit file and they all told me there's nothing they can do about it. I being jerked around by Experian. | C48: Credit reporting
A49: 8278 | B49: I am filing a complaint against Cash App ( Block , Inc. ) due to inadequate customer service and unfair practices which violate the Consumer Financial Protection Act. Cash App failed to take timely and effective mesures to prevent fraud on their platform, This has left my accounts and finances vulnerable and unprotected. Their dispute resolution process is deceptive and unfair as they did not comply with the error resolution requirements under the Electronic Fund Transfer Act and Regulation E. This has caused signifigant inconvenience and financial loss and I seek appropriate redress for these violations. | C49: Money transfer or service
A50: 8284 | B50: I Have an account in Coinbase with XXXX XXXX XXXX. Since 2 months I cant sell, transfer or buy cripto currencies because the account is under revision. I Have tried to speak with coinbase and its impossible, no answer. Calls, email... but no solutions. I would like to send my cripto currency. Thanks | C50: Bank account or service | D50: Crypto exchange (Coinbase) account lock - no category fits, forced
A51: 8287 | B51: I have provided Experian on SIX occasions with an FTC identity theft report and various police reports to Experian regarding XXXX XXXX, XXXX XXXX and the identity theft on my report. I have also reported and provided a letter from XXXX XXXX regarding the fraudulent account. Experian is ruining my credit score by refusing to remove the fraudulent items. The items from XXXX XXXX and XXXX XXXX are the result of identity theft and are ruining my credit score. Experian had been sued for this in the past. DELETE the items! | C51: Credit reporting
A52: 8291 | B52: I opened an account with XXXX XXXX in XXXX to transfer my balance from my XXXX XXXX XXXX XXXX card to, as the XXXX card offered 0 % XXXX on balance transfers. XXXX sent a check to XXXX and charged my account. XXXX deposited the check, but I never received credit on my XXXX account for the check. My XXXX account was charged on XX/XX/XXXX. Today, XX/XX/XXXX, I called XXXX to let them know that XXXX finished their investigation, and that they had sent me a letter with the results. I asked XXXX how I could send them those results, and they told me a case number on the phone with no additional information. XXXX asked for the exact account number the check was for, and XXXX told me they could not provide any information on that. I am currently still paying off both balances and not sure if any resolution is in sight. XXXX 's website gives me errors when I try to pull up information related to the transfer or disputes. | C52: Credit card
A53: 8292 | B53: Hello, I find it highly problematic that Citibank is refusing to close client 's credit card accounts. I understand that they are trying to catch up with other big retail banks in the credit card business, but I think their business practises are highly unethical and unprofessional. My detailed experience is as follows. I signed up for a Citibank credit card a couple years ago. However, I didn't really like their offerings compared to their competitors, so I rarely used the Citi credit card. Last summer, I noticed a fraudulent activity on that card which prompted me to call Citibank to close my account. However, their customer service staff were extremely resistant with my request. They kept on going in circles asking me why I wanted to close the account and started offering me things I don't need in order to keep my account open. I was in a rush when I called, so I decided not to bother closing it. A year later, I decided to call Citibank again to close the account. They did the same tactic where they kept on asking me why I wanted to close the account. I answered, " I don't use your card and I want to close it ''. However, they refused to take that as an answer. They responded : " For compliance reasons, we need to know why you want to close the account ''. I said I already told them why I want to close the account. And then they started offering me 10,000 " ThankYou points '' to prevent me from closing the account. After wasting half an hour of my time, I became very impatient and I had to tell them, this is my account and I have the right to close it. I told them that I would report the to the regulators if they refuse to close my account. Only until then, they closed my account. I find their behaviour highly manipulative and unprofessional. I want to bring this to the attention of the regulators, as I think this is highly problematic and I have not experienced similar behaviour from other banks. Regards, XXXX | C53: Credit card
A54: 8299 | B54: Citizens One Bank is purposefully making it difficult to remove PMI. I submitted a request to start the process 3 weeks ago and have not received a call, email, or secure message from the company with ALL information for removing it. They have only sent a message saying they will send another message via snail-mail. They REFUSE to give me the contact information for the PMI department. | C54: Mortgage | D54: PMI is a mortgage product
A55: 8301 | B55: I am submitting this complaint regarding an issue with my credit report that is negatively affecting my financial standing. I have made multiple attempts to resolve this matter directly with the creditor/furnisher, but they have failed to provide an adequate response. Below are the details of my complaint : XXXX. Charged-Off Account or Collection Account Creditor/Collection Agency Name : SXXXX XXXX XXXX XXXX XXXX XXXX XXXX XXXX XXXX XXXX XXXX XXXX XXXX XXXX XXXX XXXX XXXX XXXX XXXX XXXX XXXX XXXX XXXX XXXX XXXX XXXXXXXX Issue : This account was charged off/placed in collections without proper notification or validation of the debt. I requested validation of the debt per my rights under the Fair Credit Reporting Act ( FCRA ) and Fair Debt Collection Practices Act ( FDCPA ), but the creditor/collection agency failed to provide sufficient documentation. The reported balance and payment history contain inaccuracies that I have disputed with the credit bureaus, yet the creditor refuses to correct or remove the erroneous data. The account was sold to a third-party collector, yet it remains listed under the original creditor, creating duplicate reporting and unfair harm to my credit profile. I am requesting the immediate deletion of this inaccurate and unverifiable account from my credit report or proper documentation proving its validity. | C55: Credit reporting | D55: Also FDCPA validation; ask is deletion from report
A56: 8307 | B56: In XXXX of XXXX, property taxes were waived in the city of XXXX due to 100 % service connected XXXX. Penny Mac issued a refund in XXXX of XXXX for money paid to escrow for property taxes for the year. I. XX/XX/XXXX, the escrow paid the property taxes to the city of XXXX in error in the amount of XXXX. Since the end of XXXX I have called over 10 times between the lender and the city of XXXX to obtain the refund. I continually have to wait 14 business for a response that doesnt come. As of today XX/XX/XXXX. Penny mac has a cashed check with a check number for the property taxes refund and refuses to refund me even though we closed our loan out with them in the beginning of XXXX. | C56: Mortgage
A57: 8309 | B57: THIS IS NOT A DUPLICATE! same problem, same company, different co-signer. I have been asking Navient to release my cosigners for 8 months now and can not get any specifics on why they are refusing to do so. I sent a letter to Navient, which they received on XX/XX/XXXX, requesting an explanation, in detail, for why they refuse to release cosigners even though we met their stated requirements. As of today, XX/XX/XXXX, they still have not answered me. Plus they keep sending ridiculous answers for why they can not answer my questions. Playing games to drag it out longer so they get what they want. terrible, terrible, terrible, crooked, lying, stealing company. Some things they tell you only over the phone, some things they only tell you snail mail, some things they only tell you by fax, it's absolutely criminal. | C57: Consumer loan
A58: 8310 | B58: On XX/XX/XXXXXXXX while vacation in XXXX, MO we attended an owners ' meeting and a man named XXXX XXXX sold us ownership in XXXX XXXX XXXX for {$3900.00}. This company was supposed to rent out any unused XXXX XXXX points and pay us for them. After receiving our XXXX XXXX points in XXXX, I contacted or attempted to contact XXXX XXXX to find out how to proceed. I called the numbers provided on XXXX XXXXXXXX XXXX business card but the numbers are no longer in service ( XXXX and XXXX ). I also emailed XXXX and that address does not exist. I contacted the executive offices of XXXX in XXXX where we supposedly purchased ownership with XXXX XXXX and they informed us that XXXX XXXX had been fired. I had no way to get in touch with this group and I contacted the credit card company to which the {$3900.00} was charged and informed them that this was a fraudulent charge and that we were unable to contact anyone ( even the info provided on the charging line of the credit card statement ( XXXX ) and that we had not received any services from them for which we had paid. The card is a Barclays XXXX XXXX card. Barlays immediately issued a provisional credit for the {$3900.00}. On XX/XX/XXXX I received a letter from Barlays indicatingthat indicated that they had received a response to validate the transaction and that the merchant had not violated the terms and condidtions of the sales agreement and that the {$3900.00} would be reapplied to our account. Again this morning XX/XX/XXXX I attempted to contact XXXX XXXX using the email address provided on the contract and received a reply that the address does not exist ( XXXX ) and I called the phone number provided ( XXXX ) and the number has been disconnected. I am going to provide this additional information to Barclays and continue to protest the charge because evidently either this company does not exist or has gone out of business because WE HAVE NOT RECIEVED ANY SERVICES that this contract provides. | C58: Credit card
A59: 8323 | B59: Yard card finances lawn equipment through td bank. I mail my payment through my online account at XXXX XXXX every month. They applied my XXXX payment to the wrong account. I have contacted them by phone and email and they can not straighten out the problem. My account number with yard card is XXXX. The account they credited payment to was XXXX. | C59: Credit card | D59: Yard Card via TD - revolving store card; CL plausible
A60: 8326 | B60: After receiving a copy of my 3 bureau credit report in XX/XX/XXXX, I noticed that Pro Collect was reporting a balance of {$1000.00}. I am unfamiliar with this company so I reached out to them in hopes to get some clarity on this alleged amount due. During the call I was told that they are a third part and have been collecting on the account since XX/XX/XXXX. I requested, both in writing and verbally, a copy of the contract and /or validation of this account on XX/XX/XXXX and have yet to receive either. The presence of this account has made it difficult for me to obtain even the smallest amount of credit and has caused a great strain on my lifestyle. I also disputed this account directly with the 3 CB 's and they came back verified. I requested the name and documents used to verify this account well over 30 days ago. According to the FCRA it must be deleted from all reporting entities. I am requesting that Pro Collect comply with FCRA, 15 U.S.C under Section 611 ( a ) ( 5 ) ( A ) ( i ) and delete this account immediately. | C60: Credit reporting | D60: Collection tradeline + validation request; ask is FCRA deletion (edge rule)
A61: 8333 | B61: I have been dealing with only Wells Fargo and now as of XX/XX/2021, they are saying that being the servicer of the loan they can do anything, right or wrong and not be responsible. So now I am bringing XXXX XXXX XXXX in and let them see what their Servicer have been doing. | C61: Mortgage | D61: Loan type not stated; 'servicer' + Wells Fargo suggests mortgage - forced
A62: 8335 | B62: Mostly all of XXXX Ive been getting random charges of purchases clearly I wasnt making being in my hometown and the charges coming out from different states. XXXX XXXX XX/XX/XXXX there have been multiple withdrawals and purchase attempts with some actually going thru because I didnt have my card locked. XXXX of XXXX someone transferred a large amount of my funds to an unfamiliar person for well over {$600.00}! From XXXX to current I continue to get random charges of attempts with some being successful to merchants like XXXX. All of these problems came with me calling the hotline number online only to be told We will look into it and get back and never recieved any call or feedback. | C62: Bank account or service | D62: Card charges + transfer; institution/product vague
A63: 8337 | B63: I made a one time purchase at Macys and the sales person offered me this card. I explained that I did not want the card, because I would use it only at that particular moment and not anymore. I do not live in the US. The sales person guarantee that there would be no charges involved in making that application so I could use the card one time. There were no fees. I used my son 's address and told her. I was surprised with this letter from the debit collector. I reserve my rights to use a lawyer again the company if I have any further inconveniences for this matter. I hope the matter gets solved and wait for an answer. | C63: Debt collection | D63: Store card origin; thin narrative, collector letter is the trigger
A64: 8339 | B64: A loan under my name was takin out in XXXX XXXX XXXX I have filed a complaint against LVNV Funding LLC. before, and I have not gotten any help. I just sent them another message today, and asked to speak with a manger or higher up. I also wrote them a message in the past asking to talk to a manger or higher up. That never happened. My credit score continues to decrease because of this fraudulent loan, and LVNV Funding LLC does not help resolve the matter. I do not want my score to decrease again. I have also contacted other law enforcement agencies regarding this, and hope they can help me. | C64: Credit reporting
A65: 8342 | B65: On XX/XX/year>, I noticed multiple unauthorized XXXX XXXX charges on my Chime debit card ending XXXX, totaling approximately {$290.00}. I immediately turned off my card, reported the transactions, and had a replacement card issued. At the time these transactions occurred, my original card was turned off in the Chime app, meaning it should not have been able to process any debits. I submitted my official XXXX XXXX purchase history, which clearly shows no matching transactions, proving that the charges were not made on my XXXX account or any of my devices. I filed my formal dispute on XX/XX/year>, after the transactions finished pending. Chime closed the dispute in less than XXXX hours over a weekend without conducting a reasonable investigation or providing any verification data. The only proof Chime supplied was a list of transaction entries, with no device logs, IP data, or merchant authorization details connecting me to the purchases. Under Regulation XXXX ( XXXX CFR XXXX ), financial institutions must perform a reasonable investigation before denying a consumers claim. Chime and its partner bank, XXXX XXXX XXXX, XXXX, failed to meet that requirement. | C65: Bank account or service | D65: Chime debit card unauthorized charges
A66: 8345 | B66: Coinbase locked my account on XXXX to " verify my identity ''. I've had the account for many years and my portfolio is in excess of $ XXXX. I have done everything they asked to restore access to my account but they require proof of where I obtained my capital from. I do not have such documents. My seed money came from a wrongful death suit and I explained that. Ive paid my taxes every year, they have my ID and my SSN, I've sent documents of every transfer I ever made from my bank account to Coinbase. They have given me a few days to submit these documents but refuse to tell me what will happen if I can not. I have asked them, they have dodged every question and refused to even tell me what documents will satisfy them. I can not make trades or withdraw any of my money. | C66: Bank account or service | D66: Crypto exchange (Coinbase) account lock - no category fits, forced
A67: 8356 | B67: I was approved for a XXXX XXXX loan modification and had payments due in XX/XX/XXXX., XX/XX/XXXX, and XX/XX/2018. When I called to make the first payment on XX/XX/XXXX ( I had until the last day of the month ) they informed me my house had been sold in foreclosure to XXXX XXXX. I have been battling this with both Loan Depot and with XXXX XXXX ever since XX/XX/XXXX. and have been told numerous times that it was Loan Depot 's fault for not advising the foreclosure dept. They passed me off to different agents this entire time where I would have to explain the situation all over again. They sent out company wide emails while I was one the phone explaining that it was a wrongful foreclosure but nothing has come of it. XX/XX/XXXX XXXX XXXX sold my house to a renovation company and I have just received my 10 day notice to vacate. I've learned this is called Double-tracking and it is illegal. I can not find any attorney to help me for some reason. I will fight this till they kick me out of my home but this is my daughter 's home. She was born here. She is XXXX years old. I had $ XXXX in equity in the home but lost my business and had trouble making payments. I though this Flex Mod. was my saving grace and it ended up being the hardest thing I've ever dealt with in my life. Whoever reads this, I need help please | C67: Mortgage
A68: 8359 | B68: I am a borrower impacted by the Joint Consolidation Separation Loan Act I contacted Mohela about our loan # XXXX by phone the beginning of XXXX asking for a 30 day forbearance and they verbally granted it. But they are still sending a bill for it. I emailed them on XX/XX/XXXX, XX/XX/XXXX, XX/XX/XXXX, XX/XX/XXXX, XX/XX/XXXX explaining this to them and they only responded with an explanation that I already have a forbearance on this loan, but they are referring to my other loan # XXXX which is part of the pandemic forbearance. I tried calling and was placed on hold for 120 minutes and when someone answered, they took my personal information and put me on hold back at the beginning cue that said " your approximate hold time is 100 minutes. I had to go back to work and could not hold for an additional 2 hours. I also completed my annual recertification information on XXXX and they are sending me letters stating that I have not done it and increased my payment by {$300.00}. I also emailed asking for a PSLF forbearance due to our application sent in for the temporary waiver and they have not granted it. | C68: Consumer loan | D68: Joint Consolidation Loan Separation Act allows married or formerly married borrowers to split old joint federal student loans
A69: 8365 | B69: BB & T failed to notify me of an increase in my monthly mortgage payment. I continued to make monthly mortgage payments and BB & T continued to receive and accept my on time payments. In XXXX and XXXX BB & T reported my mortgage payments as not as being paid for two months to the credit rating agencies. I learned of this when I called BB & T to inquire as to why I had not received a new mortgage coupon payment book. I than wrote BB & T and informed them I never received any notification from them regarding the change in mortgage rates and its effect on my monthly mortgage payment. I requested BB & T provide proof of a delivery confirmation of mail sent to me and that it was successfully delivered. Any financial matter that could have an adverse effect on anyone 's credit rating should require a delivery confirmation. I have paid my monthly mortgage payment on time every month and BB & T has received payment before the due date. The months in questions are XXXX and XXXX 2016 which XXXX shows funds posted, received and accepted by BB & T. When spoke with a BB & T representative I was informed that the payments were posted to my account. How can funds received for on time payment by BB & T get posted and reported as late - where did my money go and why is BB & T allowed to conduct such a questionable banking practice? | C69: Credit reporting | D69: Mortgage reported late - reporting edge rule; also payment-change notice issue
A70: 8366 | B70: I applied for Chase freedom Unlimited credit card and was denied. Upon denial I contacted Chase, I spoke with a representative that told me I was denied because of my credit score and more information would be sent by mail. I received a notice by mail stating the same thing, that I was being denied due my credit score. I then sent Chase an adverse action letter and a notice of default/ opportunity to cure and they have now defaulted. The silence from Chase is XXXX. | C70: Credit card
A71: 8369 | B71: XXXX XXXX restricted my cards because someone paid the balance off on both of my credit cards without my knowledge of who it was they wanted me to submit a bank statement to prove it was not me but the card that paid the bill off in full was not mines I do not have an account with that bank after not being able to submit that statement they returned the balances back to my credit cards and close my account my accounts were in good standing at my venture card was {$2800.00} and my quick silver was {$2500.00} is what was paid off and than returned back to the original balances I tired to explain to the fraud department but nothing happen I called them everyday for XXXX weeks and they were still asking for a statement from me and I kept telling them I do not have a statement that is not my account they also tried to charge cell phones at XXXX but the card was declined this all happen in XX/XX/year> and they paid my cell phone bill for {$100.00} | C71: Credit card
A72: 8372 | B72: This is a follow-up to my existing complaint ( ID XXXX ). On XX/XX/year>, I met with XXXX XXXX ( XXXX XXXX XXXX at XXXX XXXX. XXXX XXXX XXXX ). She stated she is unable to provide any written or verbal explanation for the closure of my account, claiming the decision was not hers and she was not given any details. She confirmed the decision originated from someone above her level. On XX/XX/year>, I sent a formal demand to Old Nationals Legal Department requesting they immediately reopen and support my remaining ~ {$11000.00} in XXXX XXXX disputes. I have received no substantive response. The closure of my account while these disputes were still open has made it impossible to resolve them. I am requesting CFPB assistance in forcing Old National Bank to reopen and fully support my remaining XXXX disputes and provide a written explanation for the account closure. | C72: Bank account or service | D72: Account closure with open disputes; dispute product unclear
A73: 8379 | B73: I disputed an item due to cancelling and never receiving merchandise, Wells fargo took the word of the merchant that I did n't cancel so they reversed the credit. I felt this was unfair having being charged XXXX for something that I never received and was told would be cancelled and no further shipments. Wells Fargo wont reopen its investigation and says I did n't cancel, why would I lie? this is a large bank just bullying the little guy | C73: Credit card
A74: 8382 | B74: Validation of Debt Request - SPRINGOAKCAPXXXXXXXX XXXX XXXXXXXX XXXX XXXX XXXX XXXX XXXX XXXX XXXX I am disputing this account as inaccurate and request full validation, including the original signed agreement and complete payment history. If you can not verify this debt, you must delete it from all credit reporting agencies. Pursuant to the Fair Debt Collection Practices Act ( FDCPA ) 1006.34, I am entitled to receive verification of the debt you claim I owe. I dispute the validity of this debt and, as such, I am exercising my rights under the FDCPA to seek verification. Please provide the following information within the next 30 days : 1. The amount of the debt claimed. 2. The name of the original creditor. 3. A copy of the agreement, contract, or other instrument that created the debt. 4. Verification that you are licensed to collect debts in | C74: Debt collection
A75: 8383 | B75: XXXX servicer granted us a forbearance because of our toddlers large medical needs and recent XXXX which also happened to be during covid 19 ( my husband was out of work as well ) and said they would put the amount to the back of the loan. Over the past week, they have been trying to demand the forbearance in full because they say the loan carrier inspire home loans said its either we pay full or nothing. I have supporting documentation that states we can resume our regular payment on XX/XX/2023. They accepted a payment in XXXX {$1400.00}. Over the month, we have been trying to set up a REPAYMENT plan now that our forbearance has ended. Since they will not place it on the back of the loan like they initially told us they would. We can pay our standard {$1500.00} a month plus an extra {$1000.00} a month for a total of {$2500.00} for 12 months. And have seen no results.. inspire home loans said they need to speak to their legal team about repayment plans, ( they are trying to say {$4000.00} if they get the ok from their legal team a month even thought we only owe XXXX in forbearance and it should be able to repay over a 12 month span ) and they cant risk putting the forbearance to the back of the loan even though our house is worth double the amount owed. Inspire home loans even had the nerve to transfer us to the foreclosure department, where they told us we werent in foreclosure.. & then a servicing manager asked for the forbearance documentation that I have because she couldnt access it herself because she said loan care was hanging up on her.. its been an absolute nightmare. I even offered to pay them {$4000.00} on XX/XX/XXXX. They would not take it. | C75: Mortgage
A76: 8384 | B76: Dear NAVY FEDERAL CR UNION ], This letter serves as confirmation that the debt associated with my then account has been paid in full as of [ XX/XX/year> ]. No further balance remains on this account, and it is now considered closed. We appreciate your prompt attention to this matter. If applicable, we will notify the relevant credit reporting agencies to reflect the updated status. Please retain this letter for your records. Should you have any questions, feel free to contact me. | C76: Credit reporting
A77: 8389 | B77: My identity was compromise since XXXX I was out of the country for five years upon my return. I find out all my identity was compromised. Multiple account was opened under my name on my credit report. I reported this matter to the law-enforcement agency I received the report from the police department. I also submit a complaint to XXXX FBI I was advised by the quality report advisor from XXXX to generate and submit my report through FTC. Your time is highly appreciated. Please help me with my concern. My credit is all I have. Thank you for your time. | C77: Credit reporting
A78: 8390 | B78: They claim I activated an XXXX Rate Sale offer with a promotional rate through XX/XX/22. I did not do this. I would like to see proof and the details of this offer. It has affected how they processed my payments on balance transfers. | C78: Credit card | D78: 1. Balance transfers are a credit card feature. "It has affected how they processed my payments on balance transfers" is the strongest clue. You move debt onto a credit card; loans and bank accounts don't do balance transfers. 2. "Rate Sale offer with a promotional rate through XX/XX/22." Time-limited promotional APR offers are typical of card issuers. The customer is disputing an APR/promotional rate change, which is listed in the Protocol's Credit card scope ("APR issues"). 3. The complaint is about how the issuer treats the account. The person is disputing enrolment in an offer they didn't agree to, and how payments were then allocated. On cards, payments above the minimum go to the highest-APR balance first, so a surprise promo rate can change which balance a payment pays down. That matches "affected how they processed my payments." 4. Nothing points elsewhere. There's no credit report, collector, mortgage, loan, deposit account or transfer app involved, so no edge-case rule sends it to another category.
A79: 8392 | B79: I attempted to purchase XXXX XXXX tickets through PayPal using the Pay Later / XXXX financing option. When I completed the purchase, the PayPal screen clearly showed the transaction as DECLINED. Because it was declined, I reasonably assumed the purchase had failed. Instead of honoring the financing plan I selected, PayPal attempted to force the charge through by splitting the purchase into XXXX separate charges of approximately {$1200.00} each, all processed at the same moment. I never authorized XXXX separate charges. I authorized only XXXX financed transaction under the promotional XXXX plan. I did not receive any confirmation email, receipt, itinerary, or e-ticket from PayPal or XXXX XXXX. The airline later informed me that they sent the ticket information to an old and inactive email address unrelated to the email used for the PayPal transaction. Because the payment appeared as declined, I had no reason to expect any ticket or further action. Days later, my debit card was unexpectedly declined. When I checked my bank account, it was overdrawn by nearly {$5000.00} because PayPal had attempted to process the XXXX unauthorized charges. When I tried to dispute the issue in the PayPal app, the system would not allow me to file a claim until the charges cleared. After they cleared, I submitted the dispute, but PayPal denied all XXXX claims individually. PayPal is now attempting to collect almost {$5000.00} for charges I never authorized and for a service I never received. I am requesting CFPB assistance because PayPal failed to apply the financing option, processed multiple unauthorized transactions, caused a significant overdraft, denied my disputes, and is now threatening to send this to collections. | C79: Money transfer or service | D79: PayPal Pay Later financing + unauthorized split charges; CL plausible
A80: 8414 | B80: Pressler and Pressler in New Jersey has been pursuing me for a medical debt of roughly {$1200.00} for the past several months. I initially set up a payment plan as I receive low income and am supporting my 14 month old daughter. I set up this payment plan in response to being sued by Pressler and Pressler with no warning. After several months of being invoiced and paying them I stopped receiving invoices. With absolutely no warning I discovered that Pressler and Pressler had garnished and frozen my bank account in attempt to collect the debt. I called them to try to resolve the issue and the only thing they would allow me to do was make a payment on a payment plan, however they would not release my bank account to me, claiming that I needed to hire a lawyer to proceed. I had to pay them using a credit card, which I am not worried I can not pay because my bank account remains frozen. The gentleman I spoke to told me that if I do not make payments I will be held in contempt of court and will possibly face charges or legal action. Without my bank account I am now unable to pay for my housing, my credit card bills, and most importantly, provide for my daughter. | C80: Debt collection | D80: Frozen bank account is a result of garnishment - collection process is the subject
A81: 8418 | B81: I noticed that MRS BPO LLC reported a {$320.00} collection account on my XXXX credit report, listing XXXX as the original creditor. I do not owe this debt and have no record of having any account with XXXX. I contacted MRS BPO LLC to request validation of this debt, including proof of the original account, contract, and billing statements, but they did not provide any documentation to show that the debt is mine. Despite my request, the company continues to report this information to XXXX, which is negatively affecting my credit. I am requesting that the CFPB review this matter and require the company to either provide full verification of the debt or remove the inaccurate collection account from my credit report. | C81: Credit reporting | D81: Collection tradeline + validation; ask is removal from report
A82: 8420 | B82: On XX/XX/2023 I called XXXX XXXX to dispute information that was reporting incorrectly on my credit report. I was transferred to the Credit Reporting Department with XXXX XXXX and was told that " your account has been purged and is no longer in our system ''. I then asked if she could at least pull up my payment history on the account and she said, " No, I can't pull up anything about you in our system because your account has been purged from our system ''. On that same date, following the call with XXXX XXXX, I filed Credit Disputes with Transunion and XXXX online. I submitted a dispute letter and several files of evidence to support my claims. Transunion completed their investigation within XXXX business days and XXXX also completed theirs within XXXX business days. Neither of the Credit Agencies updated my credit reports with the disputed information although they both did make minor changes. If XXXX XXXX has told me themselves that my account was purged and removed from their system, how did Transunion and XXXX verify any of the information that is showing on my credit report or the disputed information? The credit agencies actually removed half of my payment history from the disputed account. I was showing 79 % of on time payments prior to the dispute and because much of the monthly payment history was removed, my on time payment history dropped to 52 %. This account has been closed for XXXX years and there haven't been any additional payments made on the account once it was closed. So, there's no way that my actual payment history percentage should have changed as that's not what the dispute was regarding. | C82: Credit reporting
A83: 8433 | B83: WESTLAKE FINANCIAL SERVICES is reporting on my personal credit file with ( XXXX ) credit reporting agency . This account was opened fraudulently. Ive informed all parties of the issue & provided the necessary documentation to support my claim. The credit reporting agency ( CRA ) & data furnisher ( DF ) are not complying with federal law in regards to identity theft. Additionally, the credit reporting agency & data furnisher have not provided me with any evidence of an open contract, signed contract or any valid proof this was opened, authorized or created by me. Since this is a strict violation of FCRA laws I need the account removed from my file. WESTLAKE FINANCIAL SERVI XXXX Opened XXXX XXXX, 2020 Balance {$8300.00} | C83: Credit reporting
A84: 8437 | B84: I had an account that was submitted to Midland Funding for collection. I logged into Midland Funding 's website to resolve the account. When I did this I noticed there was another account in the collections tab for XXXX XXXX with a balance of {$9000.00}. I opted to chat with a represenative and when I asked her how I dispute these charges and I didnt know the account she told me there was nothing she could do to help me. I checked my credit reports and the account isn't on them for me to dispute there so I logged back into Midland Funding and chatted with another represenative who was slightly more helpful. I explained to her that I needed to dispute the account and any/all charges associated with it. I told her that this account wasn't on my credit report and I asked for details on the account. I was told the account was opened in XXXX, closed in XXXX due to non payment and that it had been placed with their agency for collection. Now when I log back into Midland Funding the status is now " in legal collection ''. I asked repeatedly how to dispute this and finally she told me I could either file a police report ( from XXXX????? ) or file a complaint with the FTC which I wasn't aware I could do. So in summary here is an account from XXXX, I happened to resolve an account with Midland Funding and now they are persuing me for 1 ) an account I didnt open and have no knowledge of and 2 ) Interestingly enough NOW they decide to contact me for payment on this account once I've satisfied another. I think what happened was they saw that I resolved an account now they are trying to get me to pay ( from XXXX ) an account I'm asking help with disputing and they dont want to help me with it. This is fraud and all I was asking for was help, I suppose I shouldn't have expected any help from a company who plans on suing me for an account I didnt open. | C84: Debt collection | D84: Original account type not stated; complaint is debt buyer pursuing an unrecognised account + no dispute path. CC only if original product assumed.
A85: 8441 | B85: I have asked requested the following personal statement be placed in my credit report and related to all who request my report. THe statement meets the word and character requirements but the reporting agency will not place this on my report as requested. " My ID was stolen, in two security breaches. Found on the dark web, my XXXX & XXXX cards were used without authority. XXXX & XXXX were notified, provided copies of law enforcement reports obtained. I disputed the accuracy & completeness of XXXX & XXXX adverse reports to the three credit reporting agencies. Each agency gave XXXX & XXXX, notice as an adverse information furnisher. XXXX & XXXX failed to, conduct a reasonable investigation of each dispute ; review all relevant information ; modify, delete, or permanently block the reporting of XXXX & XXXX adverse information. '' | C85: Credit reporting
A86: 8444 | B86: on XX/XX/23 my phone was stolen at my neighborhood pool and the thief got into my account and transfer IRS check out of my account in the amount of XXXX. I sent in all necessary documents such as a police report and FBI report. The investigation team sent me documents of how the investigation came back as no error and it showed the IP of my phone that was stolen and the times of when the transfer happened i also had a XXXX XXXX XXXX XXXX and im seeing XXXX XXXX listed on the investigation doc & i now have a XXXX XXXX XXXX & also had an address that was 28 minutes from my home address that i have no knowledge of when the transfer happened. They also dont have the name of financial institution that initiated charge on the document. | C86: Bank account or service | D86: Unauthorized transfer from stolen phone; MT plausible
